{"x": 1153, "y": 57, "ayah": 118, "line": 1, "page": 235, "sura": 11, "width": 74, "height": 81}
{"x": 1071, "y": 59, "ayah": 118, "line": 1, "page": 235, "sura": 11, "width": 82, "height": 67}
{"x": 960, "y": 52, "ayah": 118, "line": 1, "page": 235, "sura": 11, "width": 96, "height": 86}
{"x": 839, "y": 54, "ayah": 118, "line": 1, "page": 235, "sura": 11, "width": 111, "height": 81}
{"x": 707, "y": 52, "ayah": 118, "line": 1, "page": 235, "sura": 11, "width": 120, "height": 81}
{"x": 623, "y": 42, "ayah": 118, "line": 1, "page": 235, "sura": 11, "width": 68, "height": 80}
{"x": 479, "y": 57, "ayah": 118, "line": 1, "page": 235, "sura": 11, "width": 132, "height": 76}
{"x": 478, "y": 30, "ayah": null, "line": 1, "page": 235, "sura": null, "width": -6, "height": 23}
{"x": 404, "y": 54, "ayah": 118, "line": 1, "page": 235, "sura": 11, "width": 65, "height": 78}
{"x": 273, "y": 51, "ayah": 118, "line": 1, "page": 235, "sura": 11, "width": 126, "height": 91}
{"x": 67, "y": 51, "ayah": 118, "line": 1, "page": 235, "sura": 11, "width": 193, "height": 86}
{"x": 1131, "y": 184, "ayah": null, "line": 2, "page": 235, "sura": null, "width": 101, "height": 94}
{"x": 1054, "y": 181, "ayah": 119, "line": 2, "page": 235, "sura": 11, "width": 77, "height": 98}
{"x": 983, "y": 189, "ayah": 119, "line": 2, "page": 235, "sura": 11, "width": 61, "height": 81}
{"x": 873, "y": 190, "ayah": 119, "line": 2, "page": 235, "sura": 11, "width": 98, "height": 100}
{"x": 770, "y": 181, "ayah": 119, "line": 2, "page": 235, "sura": 11, "width": 89, "height": 91}
{"x": 764, "y": 167, "ayah": null, "line": 2, "page": 235, "sura": null, "width": -5, "height": 22}
{"x": 605, "y": 190, "ayah": 119, "line": 2, "page": 235, "sura": 11, "width": 151, "height": 81}
{"x": 439, "y": 189, "ayah": 119, "line": 2, "page": 235, "sura": 11, "width": 153, "height": 82}
{"x": 445, "y": 173, "ayah": null, "line": 2, "page": 235, "sura": null, "width": -15, "height": 22}
{"x": 291, "y": 190, "ayah": 119, "line": 2, "page": 235, "sura": 11, "width": 136, "height": 81}
{"x": 181, "y": 183, "ayah": 119, "line": 2, "page": 235, "sura": 11, "width": 93, "height": 88}
{"x": 64, "y": 192, "ayah": 119, "line": 2, "page": 235, "sura": 11, "width": 109, "height": 90}
{"x": 1086, "y": 318, "ayah": 119, "line": 3, "page": 235, "sura": 11, "width": 149, "height": 76}
{"x": 938, "y": 325, "ayah": 119, "line": 3, "page": 235, "sura": 11, "width": 142, "height": 78}
{"x": 872, "y": 333, "ayah": 119, "line": 3, "page": 235, "sura": 11, "width": 58, "height": 69}
{"x": 733, "y": 322, "ayah": 119, "line": 3, "page": 235, "sura": 11, "width": 124, "height": 91}
{"x": 560, "y": 317, "ayah": 119, "line": 3, "page": 235, "sura": 11, "width": 159, "height": 92}
{"x": 402, "y": 315, "ayah": 119, "line": 3, "page": 235, "sura": 11, "width": 142, "height": 94}
{"x": 286, "y": 318, "ayah": null, "line": 3, "page": 235, "sura": null, "width": 101, "height": 94}
{"x": 186, "y": 308, "ayah": 120, "line": 3, "page": 235, "sura": 11, "width": 100, "height": 94}
{"x": 62, "y": 315, "ayah": 120, "line": 3, "page": 235, "sura": 11, "width": 109, "height": 90}
{"x": 1121, "y": 459, "ayah": 120, "line": 4, "page": 235, "sura": 11, "width": 113, "height": 79}
{"x": 1046, "y": 467, "ayah": 120, "line": 4, "page": 235, "sura": 11, "width": 56, "height": 74}
{"x": 950, "y": 451, "ayah": 120, "line": 4, "page": 235, "sura": 11, "width": 84, "height": 86}
{"x": 789, "y": 451, "ayah": 120, "line": 4, "page": 235, "sura": 11, "width": 141, "height": 97}
{"x": 735, "y": 464, "ayah": 120, "line": 4, "page": 235, "sura": 11, "width": 38, "height": 59}
{"x": 610, "y": 453, "ayah": 120, "line": 4, "page": 235, "sura": 11, "width": 109, "height": 95}
{"x": 530, "y": 493, "ayah": 120, "line": 4, "page": 235, "sura": 11, "width": 64, "height": 54}
{"x": 388, "y": 451, "ayah": 120, "line": 4, "page": 235, "sura": 11, "width": 133, "height": 89}
{"x": 380, "y": 444, "ayah": null, "line": 4, "page": 235, "sura": null, "width": -5, "height": 21}
{"x": 223, "y": 455, "ayah": 120, "line": 4, "page": 235, "sura": 11, "width": 149, "height": 82}
{"x": 169, "y": 476, "ayah": 120, "line": 4, "page": 235, "sura": 11, "width": 42, "height": 66}
{"x": 60, "y": 463, "ayah": 120, "line": 4, "page": 235, "sura": 11, "width": 95, "height": 76}
{"x": 1117, "y": 583, "ayah": 120, "line": 5, "page": 235, "sura": 11, "width": 115, "height": 87}
{"x": 902, "y": 582, "ayah": 120, "line": 5, "page": 235, "sura": 11, "width": 199, "height": 91}
{"x": 754, "y": 586, "ayah": 120, "line": 5, "page": 235, "sura": 11, "width": 143, "height": 88}
{"x": 559, "y": 593, "ayah": 120, "line": 5, "page": 235, "sura": 11, "width": 180, "height": 82}
{"x": 445, "y": 586, "ayah": null, "line": 5, "page": 235, "sura": null, "width": 101, "height": 94}
{"x": 354, "y": 587, "ayah": 121, "line": 5, "page": 235, "sura": 11, "width": 91, "height": 85}
{"x": 237, "y": 585, "ayah": 121, "line": 5, "page": 235, "sura": 11, "width": 104, "height": 97}
{"x": 189, "y": 589, "ayah": 121, "line": 5, "page": 235, "sura": 11, "width": 39, "height": 70}
{"x": 64, "y": 599, "ayah": 121, "line": 5, "page": 235, "sura": 11, "width": 124, "height": 79}
{"x": 1108, "y": 727, "ayah": 121, "line": 6, "page": 235, "sura": 11, "width": 125, "height": 80}
{"x": 1030, "y": 729, "ayah": 121, "line": 6, "page": 235, "sura": 11, "width": 68, "height": 79}
{"x": 837, "y": 716, "ayah": 121, "line": 6, "page": 235, "sura": 11, "width": 182, "height": 108}
{"x": 777, "y": 726, "ayah": 121, "line": 6, "page": 235, "sura": 11, "width": 41, "height": 88}
{"x": 617, "y": 725, "ayah": 121, "line": 6, "page": 235, "sura": 11, "width": 148, "height": 85}
{"x": 498, "y": 720, "ayah": null, "line": 6, "page": 235, "sura": null, "width": 101, "height": 94}
{"x": 298, "y": 727, "ayah": 122, "line": 6, "page": 235, "sura": 11, "width": 200, "height": 84}
{"x": 241, "y": 723, "ayah": 122, "line": 6, "page": 235, "sura": 11, "width": 41, "height": 90}
{"x": 64, "y": 727, "ayah": 122, "line": 6, "page": 235, "sura": 11, "width": 164, "height": 85}
{"x": 1130, "y": 854, "ayah": null, "line": 7, "page": 235, "sura": null, "width": 101, "height": 94}
{"x": 1035, "y": 864, "ayah": 123, "line": 7, "page": 235, "sura": 11, "width": 95, "height": 77}
{"x": 920, "y": 861, "ayah": 123, "line": 7, "page": 235, "sura": 11, "width": 102, "height": 80}
{"x": 717, "y": 860, "ayah": 123, "line": 7, "page": 235, "sura": 11, "width": 189, "height": 84}
{"x": 537, "y": 852, "ayah": 123, "line": 7, "page": 235, "sura": 11, "width": 172, "height": 96}
{"x": 412, "y": 859, "ayah": 123, "line": 7, "page": 235, "sura": 11, "width": 114, "height": 92}
{"x": 296, "y": 868, "ayah": 123, "line": 7, "page": 235, "sura": 11, "width": 100, "height": 95}
{"x": 163, "y": 850, "ayah": 123, "line": 7, "page": 235, "sura": 11, "width": 121, "height": 93}
{"x": 62, "y": 843, "ayah": 123, "line": 7, "page": 235, "sura": 11, "width": 97, "height": 88}
{"x": 1079, "y": 993, "ayah": 123, "line": 8, "page": 235, "sura": 11, "width": 154, "height": 79}
{"x": 866, "y": 988, "ayah": 123, "line": 8, "page": 235, "sura": 11, "width": 204, "height": 89}
{"x": 763, "y": 994, "ayah": 123, "line": 8, "page": 235, "sura": 11, "width": 92, "height": 81}
{"x": 760, "y": 984, "ayah": null, "line": 8, "page": 235, "sura": null, "width": -10, "height": 21}
{"x": 681, "y": 1003, "ayah": 123, "line": 8, "page": 235, "sura": 11, "width": 66, "height": 72}
{"x": 574, "y": 983, "ayah": 123, "line": 8, "page": 235, "sura": 11, "width": 94, "height": 90}
{"x": 436, "y": 1000, "ayah": 123, "line": 8, "page": 235, "sura": 11, "width": 121, "height": 91}
{"x": 350, "y": 998, "ayah": 123, "line": 8, "page": 235, "sura": 11, "width": 75, "height": 64}
{"x": 176, "y": 993, "ayah": 123, "line": 8, "page": 235, "sura": 11, "width": 161, "height": 85}
{"x": 62, "y": 988, "ayah": null, "line": 8, "page": 235, "sura": null, "width": 101, "height": 94}
{"x": 1162, "y": 1399, "ayah": 1, "line": 11, "page": 235, "sura": 12, "width": 72, "height": 79}
{"x": 1166, "y": 1373, "ayah": null, "line": 11, "page": 235, "sura": null, "width": -11, "height": 21}
{"x": 1070, "y": 1399, "ayah": 1, "line": 11, "page": 235, "sura": 12, "width": 82, "height": 74}
{"x": 942, "y": 1400, "ayah": 1, "line": 11, "page": 235, "sura": 12, "width": 119, "height": 74}
{"x": 747, "y": 1396, "ayah": 1, "line": 11, "page": 235, "sura": 12, "width": 174, "height": 92}
{"x": 613, "y": 1396, "ayah": 1, "line": 11, "page": 235, "sura": 12, "width": 121, "height": 91}
{"x": 499, "y": 1390, "ayah": null, "line": 11, "page": 235, "sura": null, "width": 101, "height": 94}
{"x": 430, "y": 1397, "ayah": 2, "line": 11, "page": 235, "sura": 12, "width": 69, "height": 87}
{"x": 313, "y": 1390, "ayah": 2, "line": 11, "page": 235, "sura": 12, "width": 115, "height": 90}
{"x": 197, "y": 1390, "ayah": 2, "line": 11, "page": 235, "sura": 12, "width": 101, "height": 88}
{"x": 62, "y": 1404, "ayah": 2, "line": 11, "page": 235, "sura": 12, "width": 125, "height": 89}
{"x": 1088, "y": 1515, "ayah": 2, "line": 12, "page": 235, "sura": 12, "width": 145, "height": 113}
{"x": 856, "y": 1525, "ayah": 2, "line": 12, "page": 235, "sura": 12, "width": 211, "height": 86}
{"x": 734, "y": 1524, "ayah": null, "line": 12, "page": 235, "sura": null, "width": 101, "height": 94}
{"x": 637, "y": 1534, "ayah": 3, "line": 12, "page": 235, "sura": 12, "width": 97, "height": 78}
{"x": 515, "y": 1526, "ayah": 3, "line": 12, "page": 235, "sura": 12, "width": 108, "height": 85}
{"x": 390, "y": 1530, "ayah": 3, "line": 12, "page": 235, "sura": 12, "width": 120, "height": 79}
{"x": 237, "y": 1524, "ayah": 3, "line": 12, "page": 235, "sura": 12, "width": 139, "height": 88}
{"x": 63, "y": 1533, "ayah": 3, "line": 12, "page": 235, "sura": 12, "width": 163, "height": 81}
{"x": 1168, "y": 1667, "ayah": 3, "line": 13, "page": 235, "sura": 12, "width": 64, "height": 87}
{"x": 1002, "y": 1657, "ayah": 3, "line": 13, "page": 235, "sura": 12, "width": 154, "height": 89}
{"x": 894, "y": 1664, "ayah": 3, "line": 13, "page": 235, "sura": 12, "width": 99, "height": 89}
{"x": 780, "y": 1664, "ayah": 3, "line": 13, "page": 235, "sura": 12, "width": 91, "height": 66}
{"x": 588, "y": 1663, "ayah": 3, "line": 13, "page": 235, "sura": 12, "width": 173, "height": 83}
{"x": 494, "y": 1672, "ayah": 3, "line": 13, "page": 235, "sura": 12, "width": 82, "height": 85}
{"x": 290, "y": 1663, "ayah": 3, "line": 13, "page": 235, "sura": 12, "width": 186, "height": 69}
{"x": 209, "y": 1699, "ayah": 3, "line": 13, "page": 235, "sura": 12, "width": 61, "height": 45}
{"x": 63, "y": 1664, "ayah": 3, "line": 13, "page": 235, "sura": 12, "width": 130, "height": 86}
{"x": 1152, "y": 1797, "ayah": 3, "line": 14, "page": 235, "sura": 12, "width": 81, "height": 85}
{"x": 911, "y": 1799, "ayah": 3, "line": 14, "page": 235, "sura": 12, "width": 229, "height": 85}
{"x": 799, "y": 1792, "ayah": null, "line": 14, "page": 235, "sura": null, "width": 101, "height": 94}
{"x": 754, "y": 1803, "ayah": 4, "line": 14, "page": 235, "sura": 12, "width": 45, "height": 81}
{"x": 668, "y": 1795, "ayah": 4, "line": 14, "page": 235, "sura": 12, "width": 70, "height": 73}
{"x": 505, "y": 1801, "ayah": 4, "line": 14, "page": 235, "sura": 12, "width": 148, "height": 83}
{"x": 397, "y": 1788, "ayah": 4, "line": 14, "page": 235, "sura": 12, "width": 100, "height": 102}
{"x": 266, "y": 1790, "ayah": 4, "line": 14, "page": 235, "sura": 12, "width": 119, "height": 92}
{"x": 198, "y": 1806, "ayah": 4, "line": 14, "page": 235, "sura": 12, "width": 58, "height": 81}
{"x": 63, "y": 1790, "ayah": 4, "line": 14, "page": 235, "sura": 12, "width": 124, "height": 89}
{"x": 1152, "y": 1925, "ayah": 4, "line": 15, "page": 235, "sura": 12, "width": 81, "height": 74}
{"x": 1037, "y": 1937, "ayah": 4, "line": 15, "page": 235, "sura": 12, "width": 112, "height": 78}
{"x": 937, "y": 1926, "ayah": 4, "line": 15, "page": 235, "sura": 12, "width": 100, "height": 90}
{"x": 741, "y": 1927, "ayah": 4, "line": 15, "page": 235, "sura": 12, "width": 189, "height": 87}
{"x": 594, "y": 1933, "ayah": 4, "line": 15, "page": 235, "sura": 12, "width": 144, "height": 84}
{"x": 458, "y": 1923, "ayah": 4, "line": 15, "page": 235, "sura": 12, "width": 136, "height": 112}
{"x": 406, "y": 1942, "ayah": 4, "line": 15, "page": 235, "sura": 12, "width": 45, "height": 77}
{"x": 171, "y": 1931, "ayah": 4, "line": 15, "page": 235, "sura": 12, "width": 225, "height": 90}
{"x": 62, "y": 1926, "ayah": null, "line": 15, "page": 235, "sura": null, "width": 101, "height": 94}
{"x": 1153, "y": 57, "ayah": 118, "line": 1, "page": 235, "sura": 11, "width": 74, "height": 81}
{"x": 1071, "y": 59, "ayah": 118, "line": 1, "page": 235, "sura": 11, "width": 82, "height": 67}
{"x": 960, "y": 52, "ayah": 118, "line": 1, "page": 235, "sura": 11, "width": 96, "height": 86}
{"x": 839, "y": 54, "ayah": 118, "line": 1, "page": 235, "sura": 11, "width": 111, "height": 81}
{"x": 707, "y": 52, "ayah": 118, "line": 1, "page": 235, "sura": 11, "width": 120, "height": 81}
{"x": 623, "y": 42, "ayah": 118, "line": 1, "page": 235, "sura": 11, "width": 68, "height": 80}
{"x": 479, "y": 57, "ayah": 118, "line": 1, "page": 235, "sura": 11, "width": 132, "height": 76}
{"x": 478, "y": 30, "ayah": null, "line": 1, "page": 235, "sura": null, "width": -6, "height": 23}
{"x": 404, "y": 54, "ayah": 118, "line": 1, "page": 235, "sura": 11, "width": 65, "height": 78}
{"x": 273, "y": 51, "ayah": 118, "line": 1, "page": 235, "sura": 11, "width": 126, "height": 91}
{"x": 67, "y": 51, "ayah": 118, "line": 1, "page": 235, "sura": 11, "width": 193, "height": 86}
{"x": 1131, "y": 184, "ayah": null, "line": 2, "page": 235, "sura": null, "width": 101, "height": 94}
{"x": 1054, "y": 181, "ayah": 119, "line": 2, "page": 235, "sura": 11, "width": 77, "height": 98}
{"x": 983, "y": 189, "ayah": 119, "line": 2, "page": 235, "sura": 11, "width": 61, "height": 81}
{"x": 873, "y": 190, "ayah": 119, "line": 2, "page": 235, "sura": 11, "width": 98, "height": 100}
{"x": 770, "y": 181, "ayah": 119, "line": 2, "page": 235, "sura": 11, "width": 89, "height": 91}
{"x": 764, "y": 167, "ayah": null, "line": 2, "page": 235, "sura": null, "width": -5, "height": 22}
{"x": 605, "y": 190, "ayah": 119, "line": 2, "page": 235, "sura": 11, "width": 151, "height": 81}
{"x": 439, "y": 189, "ayah": 119, "line": 2, "page": 235, "sura": 11, "width": 153, "height": 82}
{"x": 445, "y": 173, "ayah": null, "line": 2, "page": 235, "sura": null, "width": -15, "height": 22}
{"x": 291, "y": 190, "ayah": 119, "line": 2, "page": 235, "sura": 11, "width": 136, "height": 81}
{"x": 181, "y": 183, "ayah": 119, "line": 2, "page": 235, "sura": 11, "width": 93, "height": 88}
{"x": 64, "y": 192, "ayah": 119, "line": 2, "page": 235, "sura": 11, "width": 109, "height": 90}
{"x": 1086, "y": 318, "ayah": 119, "line": 3, "page": 235, "sura": 11, "width": 149, "height": 76}
{"x": 938, "y": 325, "ayah": 119, "line": 3, "page": 235, "sura": 11, "width": 142, "height": 78}
{"x": 872, "y": 333, "ayah": 119, "line": 3, "page": 235, "sura": 11, "width": 58, "height": 69}
{"x": 733, "y": 322, "ayah": 119, "line": 3, "page": 235, "sura": 11, "width": 124, "height": 91}
{"x": 560, "y": 317, "ayah": 119, "line": 3, "page": 235, "sura": 11, "width": 159, "height": 92}
{"x": 402, "y": 315, "ayah": 119, "line": 3, "page": 235, "sura": 11, "width": 142, "height": 94}
{"x": 286, "y": 318, "ayah": null, "line": 3, "page": 235, "sura": null, "width": 101, "height": 94}
{"x": 186, "y": 308, "ayah": 120, "line": 3, "page": 235, "sura": 11, "width": 100, "height": 94}
{"x": 62, "y": 315, "ayah": 120, "line": 3, "page": 235, "sura": 11, "width": 109, "height": 90}
{"x": 1121, "y": 459, "ayah": 120, "line": 4, "page": 235, "sura": 11, "width": 113, "height": 79}
{"x": 1046, "y": 467, "ayah": 120, "line": 4, "page": 235, "sura": 11, "width": 56, "height": 74}
{"x": 950, "y": 451, "ayah": 120, "line": 4, "page": 235, "sura": 11, "width": 84, "height": 86}
{"x": 789, "y": 451, "ayah": 120, "line": 4, "page": 235, "sura": 11, "width": 141, "height": 97}
{"x": 735, "y": 464, "ayah": 120, "line": 4, "page": 235, "sura": 11, "width": 38, "height": 59}
{"x": 610, "y": 453, "ayah": 120, "line": 4, "page": 235, "sura": 11, "width": 109, "height": 95}
{"x": 530, "y": 493, "ayah": 120, "line": 4, "page": 235, "sura": 11, "width": 64, "height": 54}
{"x": 388, "y": 451, "ayah": 120, "line": 4, "page": 235, "sura": 11, "width": 133, "height": 89}
{"x": 380, "y": 444, "ayah": null, "line": 4, "page": 235, "sura": null, "width": -5, "height": 21}
{"x": 223, "y": 455, "ayah": 120, "line": 4, "page": 235, "sura": 11, "width": 149, "height": 82}
{"x": 169, "y": 476, "ayah": 120, "line": 4, "page": 235, "sura": 11, "width": 42, "height": 66}
{"x": 60, "y": 463, "ayah": 120, "line": 4, "page": 235, "sura": 11, "width": 95, "height": 76}
{"x": 1117, "y": 583, "ayah": 120, "line": 5, "page": 235, "sura": 11, "width": 115, "height": 87}
{"x": 902, "y": 582, "ayah": 120, "line": 5, "page": 235, "sura": 11, "width": 199, "height": 91}
{"x": 754, "y": 586, "ayah": 120, "line": 5, "page": 235, "sura": 11, "width": 143, "height": 88}
{"x": 559, "y": 593, "ayah": 120, "line": 5, "page": 235, "sura": 11, "width": 180, "height": 82}
{"x": 445, "y": 586, "ayah": null, "line": 5, "page": 235, "sura": null, "width": 101, "height": 94}
{"x": 354, "y": 587, "ayah": 121, "line": 5, "page": 235, "sura": 11, "width": 91, "height": 85}
{"x": 237, "y": 585, "ayah": 121, "line": 5, "page": 235, "sura": 11, "width": 104, "height": 97}
{"x": 189, "y": 589, "ayah": 121, "line": 5, "page": 235, "sura": 11, "width": 39, "height": 70}
{"x": 64, "y": 599, "ayah": 121, "line": 5, "page": 235, "sura": 11, "width": 124, "height": 79}
{"x": 1108, "y": 727, "ayah": 121, "line": 6, "page": 235, "sura": 11, "width": 125, "height": 80}
{"x": 1030, "y": 729, "ayah": 121, "line": 6, "page": 235, "sura": 11, "width": 68, "height": 79}
{"x": 837, "y": 716, "ayah": 121, "line": 6, "page": 235, "sura": 11, "width": 182, "height": 108}
{"x": 777, "y": 726, "ayah": 121, "line": 6, "page": 235, "sura": 11, "width": 41, "height": 88}
{"x": 617, "y": 725, "ayah": 121, "line": 6, "page": 235, "sura": 11, "width": 148, "height": 85}
{"x": 498, "y": 720, "ayah": null, "line": 6, "page": 235, "sura": null, "width": 101, "height": 94}
{"x": 298, "y": 727, "ayah": 122, "line": 6, "page": 235, "sura": 11, "width": 200, "height": 84}
{"x": 241, "y": 723, "ayah": 122, "line": 6, "page": 235, "sura": 11, "width": 41, "height": 90}
{"x": 64, "y": 727, "ayah": 122, "line": 6, "page": 235, "sura": 11, "width": 164, "height": 85}
{"x": 1130, "y": 854, "ayah": null, "line": 7, "page": 235, "sura": null, "width": 101, "height": 94}
{"x": 1035, "y": 864, "ayah": 123, "line": 7, "page": 235, "sura": 11, "width": 95, "height": 77}
{"x": 920, "y": 861, "ayah": 123, "line": 7, "page": 235, "sura": 11, "width": 102, "height": 80}
{"x": 717, "y": 860, "ayah": 123, "line": 7, "page": 235, "sura": 11, "width": 189, "height": 84}
{"x": 537, "y": 852, "ayah": 123, "line": 7, "page": 235, "sura": 11, "width": 172, "height": 96}
{"x": 412, "y": 859, "ayah": 123, "line": 7, "page": 235, "sura": 11, "width": 114, "height": 92}
{"x": 296, "y": 868, "ayah": 123, "line": 7, "page": 235, "sura": 11, "width": 100, "height": 95}
{"x": 163, "y": 850, "ayah": 123, "line": 7, "page": 235, "sura": 11, "width": 121, "height": 93}
{"x": 62, "y": 843, "ayah": 123, "line": 7, "page": 235, "sura": 11, "width": 97, "height": 88}
{"x": 1079, "y": 993, "ayah": 123, "line": 8, "page": 235, "sura": 11, "width": 154, "height": 79}
{"x": 866, "y": 988, "ayah": 123, "line": 8, "page": 235, "sura": 11, "width": 204, "height": 89}
{"x": 763, "y": 994, "ayah": 123, "line": 8, "page": 235, "sura": 11, "width": 92, "height": 81}
{"x": 760, "y": 984, "ayah": null, "line": 8, "page": 235, "sura": null, "width": -10, "height": 21}
{"x": 681, "y": 1003, "ayah": 123, "line": 8, "page": 235, "sura": 11, "width": 66, "height": 72}
{"x": 574, "y": 983, "ayah": 123, "line": 8, "page": 235, "sura": 11, "width": 94, "height": 90}
{"x": 436, "y": 1000, "ayah": 123, "line": 8, "page": 235, "sura": 11, "width": 121, "height": 91}
{"x": 350, "y": 998, "ayah": 123, "line": 8, "page": 235, "sura": 11, "width": 75, "height": 64}
{"x": 176, "y": 993, "ayah": 123, "line": 8, "page": 235, "sura": 11, "width": 161, "height": 85}
{"x": 62, "y": 988, "ayah": null, "line": 8, "page": 235, "sura": null, "width": 101, "height": 94}
{"x": 1162, "y": 1399, "ayah": 1, "line": 11, "page": 235, "sura": 12, "width": 72, "height": 79}
{"x": 1166, "y": 1373, "ayah": null, "line": 11, "page": 235, "sura": null, "width": -11, "height": 21}
{"x": 1070, "y": 1399, "ayah": 1, "line": 11, "page": 235, "sura": 12, "width": 82, "height": 74}
{"x": 942, "y": 1400, "ayah": 1, "line": 11, "page": 235, "sura": 12, "width": 119, "height": 74}
{"x": 747, "y": 1396, "ayah": 1, "line": 11, "page": 235, "sura": 12, "width": 174, "height": 92}
{"x": 613, "y": 1396, "ayah": 1, "line": 11, "page": 235, "sura": 12, "width": 121, "height": 91}
{"x": 499, "y": 1390, "ayah": null, "line": 11, "page": 235, "sura": null, "width": 101, "height": 94}
{"x": 430, "y": 1397, "ayah": 2, "line": 11, "page": 235, "sura": 12, "width": 69, "height": 87}
{"x": 313, "y": 1390, "ayah": 2, "line": 11, "page": 235, "sura": 12, "width": 115, "height": 90}
{"x": 197, "y": 1390, "ayah": 2, "line": 11, "page": 235, "sura": 12, "width": 101, "height": 88}
{"x": 62, "y": 1404, "ayah": 2, "line": 11, "page": 235, "sura": 12, "width": 125, "height": 89}
{"x": 1088, "y": 1515, "ayah": 2, "line": 12, "page": 235, "sura": 12, "width": 145, "height": 113}
{"x": 856, "y": 1525, "ayah": 2, "line": 12, "page": 235, "sura": 12, "width": 211, "height": 86}
{"x": 734, "y": 1524, "ayah": null, "line": 12, "page": 235, "sura": null, "width": 101, "height": 94}
{"x": 637, "y": 1534, "ayah": 3, "line": 12, "page": 235, "sura": 12, "width": 97, "height": 78}
{"x": 515, "y": 1526, "ayah": 3, "line": 12, "page": 235, "sura": 12, "width": 108, "height": 85}
{"x": 390, "y": 1530, "ayah": 3, "line": 12, "page": 235, "sura": 12, "width": 120, "height": 79}
{"x": 237, "y": 1524, "ayah": 3, "line": 12, "page": 235, "sura": 12, "width": 139, "height": 88}
{"x": 63, "y": 1533, "ayah": 3, "line": 12, "page": 235, "sura": 12, "width": 163, "height": 81}
{"x": 1168, "y": 1667, "ayah": 3, "line": 13, "page": 235, "sura": 12, "width": 64, "height": 87}
{"x": 1002, "y": 1657, "ayah": 3, "line": 13, "page": 235, "sura": 12, "width": 154, "height": 89}
{"x": 894, "y": 1664, "ayah": 3, "line": 13, "page": 235, "sura": 12, "width": 99, "height": 89}
{"x": 780, "y": 1664, "ayah": 3, "line": 13, "page": 235, "sura": 12, "width": 91, "height": 66}
{"x": 588, "y": 1663, "ayah": 3, "line": 13, "page": 235, "sura": 12, "width": 173, "height": 83}
{"x": 494, "y": 1672, "ayah": 3, "line": 13, "page": 235, "sura": 12, "width": 82, "height": 85}
{"x": 290, "y": 1663, "ayah": 3, "line": 13, "page": 235, "sura": 12, "width": 186, "height": 69}
{"x": 209, "y": 1699, "ayah": 3, "line": 13, "page": 235, "sura": 12, "width": 61, "height": 45}
{"x": 63, "y": 1664, "ayah": 3, "line": 13, "page": 235, "sura": 12, "width": 130, "height": 86}
{"x": 1152, "y": 1797, "ayah": 3, "line": 14, "page": 235, "sura": 12, "width": 81, "height": 85}
{"x": 911, "y": 1799, "ayah": 3, "line": 14, "page": 235, "sura": 12, "width": 229, "height": 85}
{"x": 799, "y": 1792, "ayah": null, "line": 14, "page": 235, "sura": null, "width": 101, "height": 94}
{"x": 754, "y": 1803, "ayah": 4, "line": 14, "page": 235, "sura": 12, "width": 45, "height": 81}
{"x": 668, "y": 1795, "ayah": 4, "line": 14, "page": 235, "sura": 12, "width": 70, "height": 73}
{"x": 505, "y": 1801, "ayah": 4, "line": 14, "page": 235, "sura": 12, "width": 148, "height": 83}
{"x": 397, "y": 1788, "ayah": 4, "line": 14, "page": 235, "sura": 12, "width": 100, "height": 102}
{"x": 266, "y": 1790, "ayah": 4, "line": 14, "page": 235, "sura": 12, "width": 119, "height": 92}
{"x": 198, "y": 1806, "ayah": 4, "line": 14, "page": 235, "sura": 12, "width": 58, "height": 81}
{"x": 63, "y": 1790, "ayah": 4, "line": 14, "page": 235, "sura": 12, "width": 124, "height": 89}
{"x": 1152, "y": 1925, "ayah": 4, "line": 15, "page": 235, "sura": 12, "width": 81, "height": 74}
{"x": 1037, "y": 1937, "ayah": 4, "line": 15, "page": 235, "sura": 12, "width": 112, "height": 78}
{"x": 937, "y": 1926, "ayah": 4, "line": 15, "page": 235, "sura": 12, "width": 100, "height": 90}
{"x": 741, "y": 1927, "ayah": 4, "line": 15, "page": 235, "sura": 12, "width": 189, "height": 87}
{"x": 594, "y": 1933, "ayah": 4, "line": 15, "page": 235, "sura": 12, "width": 144, "height": 84}
{"x": 458, "y": 1923, "ayah": 4, "line": 15, "page": 235, "sura": 12, "width": 136, "height": 112}
{"x": 406, "y": 1942, "ayah": 4, "line": 15, "page": 235, "sura": 12, "width": 45, "height": 77}
{"x": 171, "y": 1931, "ayah": 4, "line": 15, "page": 235, "sura": 12, "width": 225, "height": 90}
{"x": 62, "y": 1926, "ayah": null, "line": 15, "page": 235, "sura": null, "width": 101, "height": 94}
