{"x": 1112, "y": 39, "ayah": 5, "line": 1, "page": 555, "sura": 63, "width": 97, "height": 90}
{"x": 1022, "y": 43, "ayah": 5, "line": 1, "page": 555, "sura": 63, "width": 82, "height": 88}
{"x": 951, "y": 32, "ayah": 5, "line": 1, "page": 555, "sura": 63, "width": 66, "height": 113}
{"x": 821, "y": 38, "ayah": 5, "line": 1, "page": 555, "sura": 63, "width": 124, "height": 83}
{"x": 632, "y": 42, "ayah": 5, "line": 1, "page": 555, "sura": 63, "width": 181, "height": 84}
{"x": 538, "y": 33, "ayah": 5, "line": 1, "page": 555, "sura": 63, "width": 97, "height": 114}
{"x": 402, "y": 31, "ayah": 5, "line": 1, "page": 555, "sura": 63, "width": 129, "height": 93}
{"x": 329, "y": 39, "ayah": 5, "line": 1, "page": 555, "sura": 63, "width": 66, "height": 86}
{"x": 252, "y": 30, "ayah": 5, "line": 1, "page": 555, "sura": 63, "width": 72, "height": 94}
{"x": 88, "y": 34, "ayah": 5, "line": 1, "page": 555, "sura": 63, "width": 157, "height": 114}
{"x": 1038, "y": 166, "ayah": 5, "line": 2, "page": 555, "sura": 63, "width": 173, "height": 109}
{"x": 858, "y": 166, "ayah": 5, "line": 2, "page": 555, "sura": 63, "width": 169, "height": 89}
{"x": 758, "y": 176, "ayah": 5, "line": 2, "page": 555, "sura": 63, "width": 92, "height": 100}
{"x": 515, "y": 167, "ayah": 5, "line": 2, "page": 555, "sura": 63, "width": 236, "height": 97}
{"x": 402, "y": 168, "ayah": null, "line": 2, "page": 555, "sura": null, "width": 101, "height": 94}
{"x": 273, "y": 176, "ayah": 6, "line": 2, "page": 555, "sura": 63, "width": 129, "height": 83}
{"x": 82, "y": 172, "ayah": 6, "line": 2, "page": 555, "sura": 63, "width": 181, "height": 97}
{"x": 968, "y": 306, "ayah": 6, "line": 3, "page": 555, "sura": 63, "width": 240, "height": 86}
{"x": 841, "y": 303, "ayah": 6, "line": 3, "page": 555, "sura": 63, "width": 111, "height": 87}
{"x": 798, "y": 296, "ayah": 6, "line": 3, "page": 555, "sura": 63, "width": 39, "height": 107}
{"x": 739, "y": 305, "ayah": 6, "line": 3, "page": 555, "sura": 63, "width": 49, "height": 106}
{"x": 549, "y": 307, "ayah": 6, "line": 3, "page": 555, "sura": 63, "width": 182, "height": 87}
{"x": 484, "y": 301, "ayah": 6, "line": 3, "page": 555, "sura": 63, "width": 69, "height": 110}
{"x": 418, "y": 305, "ayah": 6, "line": 3, "page": 555, "sura": 63, "width": 54, "height": 86}
{"x": 296, "y": 309, "ayah": 6, "line": 3, "page": 555, "sura": 63, "width": 115, "height": 88}
{"x": 224, "y": 308, "ayah": 6, "line": 3, "page": 555, "sura": 63, "width": 70, "height": 68}
{"x": 155, "y": 301, "ayah": 6, "line": 3, "page": 555, "sura": 63, "width": 66, "height": 108}
{"x": 148, "y": 298, "ayah": null, "line": 3, "page": 555, "sura": null, "width": -8, "height": 22}
{"x": 89, "y": 308, "ayah": 6, "line": 3, "page": 555, "sura": 63, "width": 48, "height": 89}
{"x": 1140, "y": 445, "ayah": 6, "line": 4, "page": 555, "sura": 63, "width": 64, "height": 65}
{"x": 1089, "y": 436, "ayah": 6, "line": 4, "page": 555, "sura": 63, "width": 43, "height": 72}
{"x": 957, "y": 448, "ayah": 6, "line": 4, "page": 555, "sura": 63, "width": 131, "height": 82}
{"x": 831, "y": 440, "ayah": 6, "line": 4, "page": 555, "sura": 63, "width": 113, "height": 107}
{"x": 532, "y": 440, "ayah": 6, "line": 4, "page": 555, "sura": 63, "width": 293, "height": 87}
{"x": 423, "y": 436, "ayah": null, "line": 4, "page": 555, "sura": null, "width": 101, "height": 94}
{"x": 347, "y": 442, "ayah": 7, "line": 4, "page": 555, "sura": 63, "width": 76, "height": 99}
{"x": 232, "y": 429, "ayah": 7, "line": 4, "page": 555, "sura": 63, "width": 104, "height": 97}
{"x": 91, "y": 439, "ayah": 7, "line": 4, "page": 555, "sura": 63, "width": 133, "height": 90}
{"x": 1167, "y": 575, "ayah": 7, "line": 5, "page": 555, "sura": 63, "width": 41, "height": 68}
{"x": 1002, "y": 573, "ayah": 7, "line": 5, "page": 555, "sura": 63, "width": 156, "height": 88}
{"x": 915, "y": 573, "ayah": 7, "line": 5, "page": 555, "sura": 63, "width": 81, "height": 85}
{"x": 840, "y": 583, "ayah": 7, "line": 5, "page": 555, "sura": 63, "width": 67, "height": 72}
{"x": 714, "y": 581, "ayah": 7, "line": 5, "page": 555, "sura": 63, "width": 117, "height": 76}
{"x": 558, "y": 585, "ayah": 7, "line": 5, "page": 555, "sura": 63, "width": 148, "height": 83}
{"x": 469, "y": 572, "ayah": 7, "line": 5, "page": 555, "sura": 63, "width": 75, "height": 87}
{"x": 332, "y": 569, "ayah": 7, "line": 5, "page": 555, "sura": 63, "width": 134, "height": 91}
{"x": 167, "y": 567, "ayah": 7, "line": 5, "page": 555, "sura": 63, "width": 154, "height": 93}
{"x": 163, "y": 546, "ayah": null, "line": 5, "page": 555, "sura": null, "width": 1, "height": 23}
{"x": 84, "y": 579, "ayah": 7, "line": 5, "page": 555, "sura": 63, "width": 77, "height": 80}
{"x": 1070, "y": 715, "ayah": 7, "line": 6, "page": 555, "sura": 63, "width": 135, "height": 92}
{"x": 857, "y": 713, "ayah": 7, "line": 6, "page": 555, "sura": 63, "width": 202, "height": 82}
{"x": 668, "y": 700, "ayah": 7, "line": 6, "page": 555, "sura": 63, "width": 181, "height": 97}
{"x": 529, "y": 710, "ayah": 7, "line": 6, "page": 555, "sura": 63, "width": 133, "height": 86}
{"x": 324, "y": 709, "ayah": 7, "line": 6, "page": 555, "sura": 63, "width": 195, "height": 84}
{"x": 275, "y": 706, "ayah": 7, "line": 6, "page": 555, "sura": 63, "width": 41, "height": 69}
{"x": 92, "y": 710, "ayah": 7, "line": 6, "page": 555, "sura": 63, "width": 175, "height": 83}
{"x": 1107, "y": 838, "ayah": null, "line": 7, "page": 555, "sura": null, "width": 100, "height": 94}
{"x": 961, "y": 842, "ayah": 8, "line": 7, "page": 555, "sura": 63, "width": 146, "height": 86}
{"x": 886, "y": 840, "ayah": 8, "line": 7, "page": 555, "sura": 63, "width": 68, "height": 96}
{"x": 729, "y": 845, "ayah": 8, "line": 7, "page": 555, "sura": 63, "width": 149, "height": 78}
{"x": 667, "y": 845, "ayah": 8, "line": 7, "page": 555, "sura": 63, "width": 61, "height": 89}
{"x": 474, "y": 840, "ayah": 8, "line": 7, "page": 555, "sura": 63, "width": 186, "height": 88}
{"x": 203, "y": 838, "ayah": 8, "line": 7, "page": 555, "sura": 63, "width": 260, "height": 100}
{"x": 82, "y": 833, "ayah": 8, "line": 7, "page": 555, "sura": 63, "width": 114, "height": 93}
{"x": 1131, "y": 987, "ayah": 8, "line": 8, "page": 555, "sura": 63, "width": 78, "height": 77}
{"x": 992, "y": 963, "ayah": 8, "line": 8, "page": 555, "sura": 63, "width": 124, "height": 86}
{"x": 980, "y": 949, "ayah": null, "line": 8, "page": 555, "sura": null, "width": 4, "height": 22}
{"x": 887, "y": 978, "ayah": 8, "line": 8, "page": 555, "sura": 63, "width": 94, "height": 81}
{"x": 743, "y": 972, "ayah": 8, "line": 8, "page": 555, "sura": 63, "width": 133, "height": 90}
{"x": 526, "y": 980, "ayah": 8, "line": 8, "page": 555, "sura": 63, "width": 212, "height": 92}
{"x": 232, "y": 979, "ayah": 8, "line": 8, "page": 555, "sura": 63, "width": 284, "height": 83}
{"x": 88, "y": 976, "ayah": 8, "line": 8, "page": 555, "sura": 63, "width": 129, "height": 87}
{"x": 936, "y": 1112, "ayah": 8, "line": 9, "page": 555, "sura": 63, "width": 272, "height": 83}
{"x": 890, "y": 1109, "ayah": 8, "line": 9, "page": 555, "sura": 63, "width": 41, "height": 71}
{"x": 737, "y": 1113, "ayah": 8, "line": 9, "page": 555, "sura": 63, "width": 153, "height": 83}
{"x": 629, "y": 1106, "ayah": null, "line": 9, "page": 555, "sura": null, "width": 101, "height": 94}
{"x": 522, "y": 1105, "ayah": 9, "line": 9, "page": 555, "sura": 63, "width": 107, "height": 91}
{"x": 410, "y": 1098, "ayah": 9, "line": 9, "page": 555, "sura": 63, "width": 103, "height": 100}
{"x": 274, "y": 1114, "ayah": 9, "line": 9, "page": 555, "sura": 63, "width": 128, "height": 81}
{"x": 221, "y": 1109, "ayah": 9, "line": 9, "page": 555, "sura": 63, "width": 41, "height": 70}
{"x": 83, "y": 1100, "ayah": 9, "line": 9, "page": 555, "sura": 63, "width": 137, "height": 103}
{"x": 1042, "y": 1239, "ayah": 9, "line": 10, "page": 555, "sura": 63, "width": 167, "height": 108}
{"x": 952, "y": 1246, "ayah": 9, "line": 10, "page": 555, "sura": 63, "width": 82, "height": 78}
{"x": 683, "y": 1237, "ayah": 9, "line": 10, "page": 555, "sura": 63, "width": 258, "height": 110}
{"x": 607, "y": 1257, "ayah": 9, "line": 10, "page": 555, "sura": 63, "width": 68, "height": 71}
{"x": 418, "y": 1255, "ayah": 9, "line": 10, "page": 555, "sura": 63, "width": 182, "height": 85}
{"x": 348, "y": 1247, "ayah": 9, "line": 10, "page": 555, "sura": 63, "width": 62, "height": 88}
{"x": 346, "y": 1233, "ayah": null, "line": 10, "page": 555, "sura": null, "width": -5, "height": 21}
{"x": 242, "y": 1252, "ayah": 9, "line": 10, "page": 555, "sura": 63, "width": 96, "height": 78}
{"x": 86, "y": 1253, "ayah": 9, "line": 10, "page": 555, "sura": 63, "width": 140, "height": 75}
{"x": 1102, "y": 1379, "ayah": 9, "line": 11, "page": 555, "sura": 63, "width": 107, "height": 81}
{"x": 915, "y": 1360, "ayah": 9, "line": 11, "page": 555, "sura": 63, "width": 179, "height": 111}
{"x": 835, "y": 1381, "ayah": 9, "line": 11, "page": 555, "sura": 63, "width": 71, "height": 102}
{"x": 601, "y": 1386, "ayah": 9, "line": 11, "page": 555, "sura": 63, "width": 225, "height": 79}
{"x": 494, "y": 1374, "ayah": null, "line": 11, "page": 555, "sura": null, "width": 101, "height": 94}
{"x": 336, "y": 1371, "ayah": 10, "line": 11, "page": 555, "sura": 63, "width": 158, "height": 94}
{"x": 279, "y": 1392, "ayah": 10, "line": 11, "page": 555, "sura": 63, "width": 53, "height": 70}
{"x": 255, "y": 1385, "ayah": 10, "line": 11, "page": 555, "sura": 63, "width": 24, "height": 60}
{"x": 88, "y": 1370, "ayah": 10, "line": 11, "page": 555, "sura": 63, "width": 164, "height": 112}
{"x": 1148, "y": 1530, "ayah": 10, "line": 12, "page": 555, "sura": 63, "width": 59, "height": 68}
{"x": 1061, "y": 1516, "ayah": 10, "line": 12, "page": 555, "sura": 63, "width": 79, "height": 93}
{"x": 1006, "y": 1511, "ayah": 10, "line": 12, "page": 555, "sura": 63, "width": 49, "height": 79}
{"x": 863, "y": 1502, "ayah": 10, "line": 12, "page": 555, "sura": 63, "width": 136, "height": 94}
{"x": 716, "y": 1505, "ayah": 10, "line": 12, "page": 555, "sura": 63, "width": 141, "height": 109}
{"x": 565, "y": 1515, "ayah": 10, "line": 12, "page": 555, "sura": 63, "width": 144, "height": 85}
{"x": 426, "y": 1508, "ayah": 10, "line": 12, "page": 555, "sura": 63, "width": 130, "height": 91}
{"x": 334, "y": 1523, "ayah": 10, "line": 12, "page": 555, "sura": 63, "width": 84, "height": 80}
{"x": 231, "y": 1514, "ayah": 10, "line": 12, "page": 555, "sura": 63, "width": 91, "height": 85}
{"x": 89, "y": 1503, "ayah": 10, "line": 12, "page": 555, "sura": 63, "width": 134, "height": 102}
{"x": 1150, "y": 1649, "ayah": 10, "line": 13, "page": 555, "sura": 63, "width": 58, "height": 92}
{"x": 1054, "y": 1644, "ayah": 10, "line": 13, "page": 555, "sura": 63, "width": 87, "height": 107}
{"x": 936, "y": 1648, "ayah": 10, "line": 13, "page": 555, "sura": 63, "width": 112, "height": 105}
{"x": 688, "y": 1633, "ayah": 10, "line": 13, "page": 555, "sura": 63, "width": 238, "height": 89}
{"x": 559, "y": 1638, "ayah": 10, "line": 13, "page": 555, "sura": 63, "width": 122, "height": 96}
{"x": 491, "y": 1653, "ayah": 10, "line": 13, "page": 555, "sura": 63, "width": 63, "height": 81}
{"x": 275, "y": 1648, "ayah": 10, "line": 13, "page": 555, "sura": 63, "width": 212, "height": 83}
{"x": 166, "y": 1642, "ayah": null, "line": 13, "page": 555, "sura": null, "width": 101, "height": 94}
{"x": 89, "y": 1650, "ayah": 11, "line": 13, "page": 555, "sura": 63, "width": 77, "height": 82}
{"x": 1095, "y": 1788, "ayah": 11, "line": 14, "page": 555, "sura": 63, "width": 109, "height": 81}
{"x": 1032, "y": 1783, "ayah": 11, "line": 14, "page": 555, "sura": 63, "width": 63, "height": 97}
{"x": 925, "y": 1788, "ayah": 11, "line": 14, "page": 555, "sura": 63, "width": 104, "height": 61}
{"x": 758, "y": 1775, "ayah": 11, "line": 14, "page": 555, "sura": 63, "width": 154, "height": 94}
{"x": 774, "y": 1783, "ayah": 11, "line": 14, "page": 555, "sura": 63, "width": 80, "height": 75}
{"x": 633, "y": 1775, "ayah": 11, "line": 14, "page": 555, "sura": 63, "width": 130, "height": 87}
{"x": 625, "y": 1766, "ayah": null, "line": 14, "page": 555, "sura": null, "width": 2, "height": 21}
{"x": 521, "y": 1783, "ayah": 11, "line": 14, "page": 555, "sura": 63, "width": 103, "height": 83}
{"x": 405, "y": 1784, "ayah": 11, "line": 14, "page": 555, "sura": 63, "width": 113, "height": 91}
{"x": 353, "y": 1791, "ayah": 11, "line": 14, "page": 555, "sura": 63, "width": 55, "height": 82}
{"x": 198, "y": 1781, "ayah": 11, "line": 14, "page": 555, "sura": 63, "width": 150, "height": 86}
{"x": 90, "y": 1776, "ayah": null, "line": 14, "page": 555, "sura": null, "width": 101, "height": 94}
