{"x": 1141, "y": 47, "ayah": 65, "line": 1, "page": 119, "sura": 5, "width": 76, "height": 77}
{"x": 1083, "y": 39, "ayah": 65, "line": 1, "page": 119, "sura": 5, "width": 49, "height": 78}
{"x": 969, "y": 36, "ayah": 65, "line": 1, "page": 119, "sura": 5, "width": 99, "height": 87}
{"x": 705, "y": 42, "ayah": 65, "line": 1, "page": 119, "sura": 5, "width": 261, "height": 93}
{"x": 558, "y": 48, "ayah": 65, "line": 1, "page": 119, "sura": 5, "width": 134, "height": 75}
{"x": 411, "y": 37, "ayah": 65, "line": 1, "page": 119, "sura": 5, "width": 138, "height": 86}
{"x": 199, "y": 30, "ayah": 65, "line": 1, "page": 119, "sura": 5, "width": 201, "height": 94}
{"x": 87, "y": 44, "ayah": 65, "line": 1, "page": 119, "sura": 5, "width": 104, "height": 95}
{"x": 1028, "y": 189, "ayah": 65, "line": 2, "page": 119, "sura": 5, "width": 187, "height": 84}
{"x": 753, "y": 174, "ayah": 65, "line": 2, "page": 119, "sura": 5, "width": 260, "height": 83}
{"x": 618, "y": 176, "ayah": 65, "line": 2, "page": 119, "sura": 5, "width": 135, "height": 86}
{"x": 467, "y": 177, "ayah": 65, "line": 2, "page": 119, "sura": 5, "width": 139, "height": 90}
{"x": 359, "y": 170, "ayah": null, "line": 2, "page": 119, "sura": null, "width": 100, "height": 94}
{"x": 278, "y": 176, "ayah": 66, "line": 2, "page": 119, "sura": 5, "width": 81, "height": 83}
{"x": 197, "y": 174, "ayah": 66, "line": 2, "page": 119, "sura": 5, "width": 81, "height": 102}
{"x": 87, "y": 177, "ayah": 66, "line": 2, "page": 119, "sura": 5, "width": 98, "height": 80}
{"x": 1072, "y": 311, "ayah": 66, "line": 3, "page": 119, "sura": 5, "width": 144, "height": 80}
{"x": 855, "y": 310, "ayah": 66, "line": 3, "page": 119, "sura": 5, "width": 202, "height": 96}
{"x": 760, "y": 311, "ayah": 66, "line": 3, "page": 119, "sura": 5, "width": 83, "height": 77}
{"x": 673, "y": 295, "ayah": 66, "line": 3, "page": 119, "sura": 5, "width": 83, "height": 112}
{"x": 560, "y": 309, "ayah": 66, "line": 3, "page": 119, "sura": 5, "width": 100, "height": 103}
{"x": 491, "y": 327, "ayah": 66, "line": 3, "page": 119, "sura": 5, "width": 58, "height": 74}
{"x": 378, "y": 316, "ayah": 66, "line": 3, "page": 119, "sura": 5, "width": 104, "height": 96}
{"x": 157, "y": 303, "ayah": 66, "line": 3, "page": 119, "sura": 5, "width": 210, "height": 87}
{"x": 88, "y": 353, "ayah": 66, "line": 3, "page": 119, "sura": 5, "width": 60, "height": 45}
{"x": 1067, "y": 445, "ayah": 66, "line": 4, "page": 119, "sura": 5, "width": 147, "height": 91}
{"x": 969, "y": 458, "ayah": 66, "line": 4, "page": 119, "sura": 5, "width": 91, "height": 75}
{"x": 868, "y": 440, "ayah": 66, "line": 4, "page": 119, "sura": 5, "width": 95, "height": 89}
{"x": 695, "y": 437, "ayah": 66, "line": 4, "page": 119, "sura": 5, "width": 162, "height": 102}
{"x": 705, "y": 452, "ayah": null, "line": 4, "page": 119, "sura": null, "width": -18, "height": 21}
{"x": 587, "y": 459, "ayah": 66, "line": 4, "page": 119, "sura": 5, "width": 97, "height": 86}
{"x": 509, "y": 439, "ayah": 66, "line": 4, "page": 119, "sura": 5, "width": 69, "height": 73}
{"x": 312, "y": 436, "ayah": 66, "line": 4, "page": 119, "sura": 5, "width": 191, "height": 91}
{"x": 311, "y": 418, "ayah": null, "line": 4, "page": 119, "sura": null, "width": -4, "height": 24}
{"x": 189, "y": 440, "ayah": 66, "line": 4, "page": 119, "sura": 5, "width": 115, "height": 95}
{"x": 85, "y": 454, "ayah": 66, "line": 4, "page": 119, "sura": 5, "width": 99, "height": 88}
{"x": 1134, "y": 586, "ayah": 66, "line": 5, "page": 119, "sura": 5, "width": 80, "height": 59}
{"x": 1087, "y": 590, "ayah": 66, "line": 5, "page": 119, "sura": 5, "width": 38, "height": 54}
{"x": 931, "y": 579, "ayah": 66, "line": 5, "page": 119, "sura": 5, "width": 152, "height": 81}
{"x": 812, "y": 572, "ayah": null, "line": 5, "page": 119, "sura": null, "width": 102, "height": 94}
{"x": 738, "y": 584, "ayah": null, "line": 5, "page": 119, "sura": null, "width": 74, "height": 69}
{"x": 621, "y": 573, "ayah": 67, "line": 5, "page": 119, "sura": 5, "width": 102, "height": 89}
{"x": 461, "y": 577, "ayah": 67, "line": 5, "page": 119, "sura": 5, "width": 148, "height": 82}
{"x": 393, "y": 582, "ayah": 67, "line": 5, "page": 119, "sura": 5, "width": 58, "height": 93}
{"x": 336, "y": 584, "ayah": 67, "line": 5, "page": 119, "sura": 5, "width": 46, "height": 61}
{"x": 251, "y": 563, "ayah": 67, "line": 5, "page": 119, "sura": 5, "width": 82, "height": 109}
{"x": 89, "y": 576, "ayah": 67, "line": 5, "page": 119, "sura": 5, "width": 154, "height": 93}
{"x": 1160, "y": 753, "ayah": 67, "line": 6, "page": 119, "sura": 5, "width": 55, "height": 46}
{"x": 1061, "y": 715, "ayah": 67, "line": 6, "page": 119, "sura": 5, "width": 90, "height": 92}
{"x": 1059, "y": 689, "ayah": null, "line": 6, "page": 119, "sura": null, "width": -6, "height": 24}
{"x": 966, "y": 714, "ayah": 67, "line": 6, "page": 119, "sura": 5, "width": 84, "height": 85}
{"x": 903, "y": 698, "ayah": 67, "line": 6, "page": 119, "sura": 5, "width": 51, "height": 89}
{"x": 791, "y": 707, "ayah": 67, "line": 6, "page": 119, "sura": 5, "width": 108, "height": 87}
{"x": 736, "y": 707, "ayah": 67, "line": 6, "page": 119, "sura": 5, "width": 49, "height": 71}
{"x": 614, "y": 707, "ayah": 67, "line": 6, "page": 119, "sura": 5, "width": 111, "height": 83}
{"x": 432, "y": 711, "ayah": 67, "line": 6, "page": 119, "sura": 5, "width": 172, "height": 90}
{"x": 443, "y": 689, "ayah": null, "line": 6, "page": 119, "sura": null, "width": -12, "height": 22}
{"x": 325, "y": 714, "ayah": 67, "line": 6, "page": 119, "sura": 5, "width": 103, "height": 75}
{"x": 83, "y": 714, "ayah": 67, "line": 6, "page": 119, "sura": 5, "width": 232, "height": 80}
{"x": 1158, "y": 855, "ayah": 67, "line": 7, "page": 119, "sura": 5, "width": 57, "height": 74}
{"x": 1025, "y": 845, "ayah": 67, "line": 7, "page": 119, "sura": 5, "width": 125, "height": 88}
{"x": 1020, "y": 847, "ayah": null, "line": 7, "page": 119, "sura": null, "width": -3, "height": 23}
{"x": 965, "y": 847, "ayah": 67, "line": 7, "page": 119, "sura": 5, "width": 49, "height": 90}
{"x": 888, "y": 850, "ayah": 67, "line": 7, "page": 119, "sura": 5, "width": 65, "height": 63}
{"x": 838, "y": 843, "ayah": 67, "line": 7, "page": 119, "sura": 5, "width": 43, "height": 72}
{"x": 713, "y": 855, "ayah": 67, "line": 7, "page": 119, "sura": 5, "width": 120, "height": 75}
{"x": 599, "y": 845, "ayah": 67, "line": 7, "page": 119, "sura": 5, "width": 106, "height": 96}
{"x": 405, "y": 846, "ayah": 67, "line": 7, "page": 119, "sura": 5, "width": 186, "height": 96}
{"x": 289, "y": 840, "ayah": null, "line": 7, "page": 119, "sura": null, "width": 101, "height": 94}
{"x": 217, "y": 836, "ayah": 68, "line": 7, "page": 119, "sura": 5, "width": 72, "height": 91}
{"x": 88, "y": 845, "ayah": 68, "line": 7, "page": 119, "sura": 5, "width": 124, "height": 86}
{"x": 1054, "y": 981, "ayah": 68, "line": 8, "page": 119, "sura": 5, "width": 164, "height": 92}
{"x": 936, "y": 981, "ayah": 68, "line": 8, "page": 119, "sura": 5, "width": 102, "height": 103}
{"x": 862, "y": 990, "ayah": 68, "line": 8, "page": 119, "sura": 5, "width": 65, "height": 77}
{"x": 754, "y": 987, "ayah": 68, "line": 8, "page": 119, "sura": 5, "width": 96, "height": 82}
{"x": 657, "y": 981, "ayah": 68, "line": 8, "page": 119, "sura": 5, "width": 88, "height": 83}
{"x": 513, "y": 971, "ayah": 68, "line": 8, "page": 119, "sura": 5, "width": 133, "height": 97}
{"x": 337, "y": 980, "ayah": 68, "line": 8, "page": 119, "sura": 5, "width": 159, "height": 82}
{"x": 86, "y": 979, "ayah": 68, "line": 8, "page": 119, "sura": 5, "width": 235, "height": 93}
{"x": 1141, "y": 1120, "ayah": 68, "line": 9, "page": 119, "sura": 5, "width": 75, "height": 75}
{"x": 1050, "y": 1102, "ayah": 68, "line": 9, "page": 119, "sura": 5, "width": 82, "height": 108}
{"x": 909, "y": 1111, "ayah": 68, "line": 9, "page": 119, "sura": 5, "width": 124, "height": 103}
{"x": 842, "y": 1132, "ayah": 68, "line": 9, "page": 119, "sura": 5, "width": 56, "height": 68}
{"x": 711, "y": 1110, "ayah": 68, "line": 9, "page": 119, "sura": 5, "width": 120, "height": 101}
{"x": 704, "y": 1113, "ayah": null, "line": 9, "page": 119, "sura": null, "width": -3, "height": 24}
{"x": 446, "y": 1117, "ayah": 68, "line": 9, "page": 119, "sura": 5, "width": 252, "height": 94}
{"x": 350, "y": 1109, "ayah": 68, "line": 9, "page": 119, "sura": 5, "width": 88, "height": 92}
{"x": 237, "y": 1124, "ayah": 68, "line": 9, "page": 119, "sura": 5, "width": 101, "height": 84}
{"x": 183, "y": 1118, "ayah": 68, "line": 9, "page": 119, "sura": 5, "width": 45, "height": 61}
{"x": 87, "y": 1102, "ayah": 68, "line": 9, "page": 119, "sura": 5, "width": 88, "height": 106}
{"x": 1114, "y": 1254, "ayah": 68, "line": 10, "page": 119, "sura": 5, "width": 104, "height": 84}
{"x": 1039, "y": 1289, "ayah": 68, "line": 10, "page": 119, "sura": 5, "width": 60, "height": 41}
{"x": 934, "y": 1254, "ayah": 68, "line": 10, "page": 119, "sura": 5, "width": 95, "height": 87}
{"x": 771, "y": 1251, "ayah": 68, "line": 10, "page": 119, "sura": 5, "width": 151, "height": 78}
{"x": 642, "y": 1240, "ayah": 68, "line": 10, "page": 119, "sura": 5, "width": 118, "height": 89}
{"x": 632, "y": 1228, "ayah": null, "line": 10, "page": 119, "sura": null, "width": 3, "height": 23}
{"x": 569, "y": 1250, "ayah": 68, "line": 10, "page": 119, "sura": 5, "width": 63, "height": 70}
{"x": 470, "y": 1235, "ayah": 68, "line": 10, "page": 119, "sura": 5, "width": 92, "height": 91}
{"x": 398, "y": 1258, "ayah": 68, "line": 10, "page": 119, "sura": 5, "width": 66, "height": 76}
{"x": 263, "y": 1251, "ayah": 68, "line": 10, "page": 119, "sura": 5, "width": 124, "height": 82}
{"x": 85, "y": 1246, "ayah": 68, "line": 10, "page": 119, "sura": 5, "width": 172, "height": 95}
{"x": 1117, "y": 1376, "ayah": null, "line": 11, "page": 119, "sura": null, "width": 101, "height": 94}
{"x": 1059, "y": 1382, "ayah": 69, "line": 11, "page": 119, "sura": 5, "width": 58, "height": 85}
{"x": 947, "y": 1373, "ayah": 69, "line": 11, "page": 119, "sura": 5, "width": 102, "height": 95}
{"x": 806, "y": 1384, "ayah": 69, "line": 11, "page": 119, "sura": 5, "width": 129, "height": 80}
{"x": 595, "y": 1369, "ayah": 69, "line": 11, "page": 119, "sura": 5, "width": 203, "height": 97}
{"x": 478, "y": 1385, "ayah": 69, "line": 11, "page": 119, "sura": 5, "width": 108, "height": 73}
{"x": 265, "y": 1385, "ayah": 69, "line": 11, "page": 119, "sura": 5, "width": 205, "height": 88}
{"x": 83, "y": 1384, "ayah": 69, "line": 11, "page": 119, "sura": 5, "width": 169, "height": 80}
{"x": 1160, "y": 1533, "ayah": 69, "line": 12, "page": 119, "sura": 5, "width": 60, "height": 62}
{"x": 967, "y": 1532, "ayah": 69, "line": 12, "page": 119, "sura": 5, "width": 177, "height": 69}
{"x": 878, "y": 1520, "ayah": 69, "line": 12, "page": 119, "sura": 5, "width": 81, "height": 84}
{"x": 712, "y": 1518, "ayah": 69, "line": 12, "page": 119, "sura": 5, "width": 153, "height": 82}
{"x": 575, "y": 1517, "ayah": 69, "line": 12, "page": 119, "sura": 5, "width": 129, "height": 95}
{"x": 432, "y": 1523, "ayah": 69, "line": 12, "page": 119, "sura": 5, "width": 141, "height": 80}
{"x": 288, "y": 1520, "ayah": 69, "line": 12, "page": 119, "sura": 5, "width": 137, "height": 80}
{"x": 212, "y": 1515, "ayah": 69, "line": 12, "page": 119, "sura": 5, "width": 61, "height": 71}
{"x": 85, "y": 1507, "ayah": 69, "line": 12, "page": 119, "sura": 5, "width": 125, "height": 90}
{"x": 1065, "y": 1654, "ayah": 69, "line": 13, "page": 119, "sura": 5, "width": 152, "height": 90}
{"x": 988, "y": 1649, "ayah": 69, "line": 13, "page": 119, "sura": 5, "width": 67, "height": 76}
{"x": 906, "y": 1653, "ayah": 69, "line": 13, "page": 119, "sura": 5, "width": 74, "height": 94}
{"x": 754, "y": 1647, "ayah": 69, "line": 13, "page": 119, "sura": 5, "width": 140, "height": 85}
{"x": 633, "y": 1644, "ayah": null, "line": 13, "page": 119, "sura": null, "width": 102, "height": 94}
{"x": 508, "y": 1648, "ayah": 70, "line": 13, "page": 119, "sura": 5, "width": 125, "height": 69}
{"x": 348, "y": 1646, "ayah": 70, "line": 13, "page": 119, "sura": 5, "width": 147, "height": 72}
{"x": 161, "y": 1655, "ayah": 70, "line": 13, "page": 119, "sura": 5, "width": 171, "height": 81}
{"x": 85, "y": 1666, "ayah": 70, "line": 13, "page": 119, "sura": 5, "width": 67, "height": 80}
{"x": 1051, "y": 1793, "ayah": 70, "line": 14, "page": 119, "sura": 5, "width": 166, "height": 84}
{"x": 859, "y": 1778, "ayah": 70, "line": 14, "page": 119, "sura": 5, "width": 183, "height": 84}
{"x": 753, "y": 1787, "ayah": 70, "line": 14, "page": 119, "sura": 5, "width": 98, "height": 96}
{"x": 622, "y": 1783, "ayah": 70, "line": 14, "page": 119, "sura": 5, "width": 117, "height": 78}
{"x": 612, "y": 1772, "ayah": null, "line": 14, "page": 119, "sura": null, "width": 3, "height": 24}
{"x": 472, "y": 1777, "ayah": 70, "line": 14, "page": 119, "sura": 5, "width": 140, "height": 75}
{"x": 303, "y": 1785, "ayah": 70, "line": 14, "page": 119, "sura": 5, "width": 157, "height": 98}
{"x": 167, "y": 1783, "ayah": 70, "line": 14, "page": 119, "sura": 5, "width": 127, "height": 82}
{"x": 87, "y": 1792, "ayah": 70, "line": 14, "page": 119, "sura": 5, "width": 70, "height": 80}
{"x": 1175, "y": 1919, "ayah": 70, "line": 15, "page": 119, "sura": 5, "width": 43, "height": 66}
{"x": 1033, "y": 1921, "ayah": 70, "line": 15, "page": 119, "sura": 5, "width": 138, "height": 79}
{"x": 865, "y": 1911, "ayah": 70, "line": 15, "page": 119, "sura": 5, "width": 156, "height": 108}
{"x": 745, "y": 1912, "ayah": 70, "line": 15, "page": 119, "sura": 5, "width": 104, "height": 101}
{"x": 536, "y": 1905, "ayah": 70, "line": 15, "page": 119, "sura": 5, "width": 197, "height": 94}
{"x": 392, "y": 1911, "ayah": 70, "line": 15, "page": 119, "sura": 5, "width": 131, "height": 104}
{"x": 209, "y": 1917, "ayah": 70, "line": 15, "page": 119, "sura": 5, "width": 168, "height": 83}
{"x": 84, "y": 1912, "ayah": null, "line": 15, "page": 119, "sura": null, "width": 101, "height": 94}
{"x": 1141, "y": 47, "ayah": 65, "line": 1, "page": 119, "sura": 5, "width": 76, "height": 77}
{"x": 1083, "y": 39, "ayah": 65, "line": 1, "page": 119, "sura": 5, "width": 49, "height": 78}
{"x": 969, "y": 36, "ayah": 65, "line": 1, "page": 119, "sura": 5, "width": 99, "height": 87}
{"x": 705, "y": 42, "ayah": 65, "line": 1, "page": 119, "sura": 5, "width": 261, "height": 93}
{"x": 558, "y": 48, "ayah": 65, "line": 1, "page": 119, "sura": 5, "width": 134, "height": 75}
{"x": 411, "y": 37, "ayah": 65, "line": 1, "page": 119, "sura": 5, "width": 138, "height": 86}
{"x": 199, "y": 30, "ayah": 65, "line": 1, "page": 119, "sura": 5, "width": 201, "height": 94}
{"x": 87, "y": 44, "ayah": 65, "line": 1, "page": 119, "sura": 5, "width": 104, "height": 95}
{"x": 1028, "y": 189, "ayah": 65, "line": 2, "page": 119, "sura": 5, "width": 187, "height": 84}
{"x": 753, "y": 174, "ayah": 65, "line": 2, "page": 119, "sura": 5, "width": 260, "height": 83}
{"x": 618, "y": 176, "ayah": 65, "line": 2, "page": 119, "sura": 5, "width": 135, "height": 86}
{"x": 467, "y": 177, "ayah": 65, "line": 2, "page": 119, "sura": 5, "width": 139, "height": 90}
{"x": 359, "y": 170, "ayah": null, "line": 2, "page": 119, "sura": null, "width": 100, "height": 94}
{"x": 278, "y": 176, "ayah": 66, "line": 2, "page": 119, "sura": 5, "width": 81, "height": 83}
{"x": 197, "y": 174, "ayah": 66, "line": 2, "page": 119, "sura": 5, "width": 81, "height": 102}
{"x": 87, "y": 177, "ayah": 66, "line": 2, "page": 119, "sura": 5, "width": 98, "height": 80}
{"x": 1072, "y": 311, "ayah": 66, "line": 3, "page": 119, "sura": 5, "width": 144, "height": 80}
{"x": 855, "y": 310, "ayah": 66, "line": 3, "page": 119, "sura": 5, "width": 202, "height": 96}
{"x": 760, "y": 311, "ayah": 66, "line": 3, "page": 119, "sura": 5, "width": 83, "height": 77}
{"x": 673, "y": 295, "ayah": 66, "line": 3, "page": 119, "sura": 5, "width": 83, "height": 112}
{"x": 560, "y": 309, "ayah": 66, "line": 3, "page": 119, "sura": 5, "width": 100, "height": 103}
{"x": 491, "y": 327, "ayah": 66, "line": 3, "page": 119, "sura": 5, "width": 58, "height": 74}
{"x": 378, "y": 316, "ayah": 66, "line": 3, "page": 119, "sura": 5, "width": 104, "height": 96}
{"x": 157, "y": 303, "ayah": 66, "line": 3, "page": 119, "sura": 5, "width": 210, "height": 87}
{"x": 88, "y": 353, "ayah": 66, "line": 3, "page": 119, "sura": 5, "width": 60, "height": 45}
{"x": 1067, "y": 445, "ayah": 66, "line": 4, "page": 119, "sura": 5, "width": 147, "height": 91}
{"x": 969, "y": 458, "ayah": 66, "line": 4, "page": 119, "sura": 5, "width": 91, "height": 75}
{"x": 868, "y": 440, "ayah": 66, "line": 4, "page": 119, "sura": 5, "width": 95, "height": 89}
{"x": 695, "y": 437, "ayah": 66, "line": 4, "page": 119, "sura": 5, "width": 162, "height": 102}
{"x": 705, "y": 452, "ayah": null, "line": 4, "page": 119, "sura": null, "width": -18, "height": 21}
{"x": 587, "y": 459, "ayah": 66, "line": 4, "page": 119, "sura": 5, "width": 97, "height": 86}
{"x": 509, "y": 439, "ayah": 66, "line": 4, "page": 119, "sura": 5, "width": 69, "height": 73}
{"x": 312, "y": 436, "ayah": 66, "line": 4, "page": 119, "sura": 5, "width": 191, "height": 91}
{"x": 311, "y": 418, "ayah": null, "line": 4, "page": 119, "sura": null, "width": -4, "height": 24}
{"x": 189, "y": 440, "ayah": 66, "line": 4, "page": 119, "sura": 5, "width": 115, "height": 95}
{"x": 85, "y": 454, "ayah": 66, "line": 4, "page": 119, "sura": 5, "width": 99, "height": 88}
{"x": 1134, "y": 586, "ayah": 66, "line": 5, "page": 119, "sura": 5, "width": 80, "height": 59}
{"x": 1087, "y": 590, "ayah": 66, "line": 5, "page": 119, "sura": 5, "width": 38, "height": 54}
{"x": 931, "y": 579, "ayah": 66, "line": 5, "page": 119, "sura": 5, "width": 152, "height": 81}
{"x": 812, "y": 572, "ayah": null, "line": 5, "page": 119, "sura": null, "width": 102, "height": 94}
{"x": 738, "y": 584, "ayah": null, "line": 5, "page": 119, "sura": null, "width": 74, "height": 69}
{"x": 621, "y": 573, "ayah": 67, "line": 5, "page": 119, "sura": 5, "width": 102, "height": 89}
{"x": 461, "y": 577, "ayah": 67, "line": 5, "page": 119, "sura": 5, "width": 148, "height": 82}
{"x": 393, "y": 582, "ayah": 67, "line": 5, "page": 119, "sura": 5, "width": 58, "height": 93}
{"x": 336, "y": 584, "ayah": 67, "line": 5, "page": 119, "sura": 5, "width": 46, "height": 61}
{"x": 251, "y": 563, "ayah": 67, "line": 5, "page": 119, "sura": 5, "width": 82, "height": 109}
{"x": 89, "y": 576, "ayah": 67, "line": 5, "page": 119, "sura": 5, "width": 154, "height": 93}
{"x": 1160, "y": 753, "ayah": 67, "line": 6, "page": 119, "sura": 5, "width": 55, "height": 46}
{"x": 1061, "y": 715, "ayah": 67, "line": 6, "page": 119, "sura": 5, "width": 90, "height": 92}
{"x": 1059, "y": 689, "ayah": null, "line": 6, "page": 119, "sura": null, "width": -6, "height": 24}
{"x": 966, "y": 714, "ayah": 67, "line": 6, "page": 119, "sura": 5, "width": 84, "height": 85}
{"x": 903, "y": 698, "ayah": 67, "line": 6, "page": 119, "sura": 5, "width": 51, "height": 89}
{"x": 791, "y": 707, "ayah": 67, "line": 6, "page": 119, "sura": 5, "width": 108, "height": 87}
{"x": 736, "y": 707, "ayah": 67, "line": 6, "page": 119, "sura": 5, "width": 49, "height": 71}
{"x": 614, "y": 707, "ayah": 67, "line": 6, "page": 119, "sura": 5, "width": 111, "height": 83}
{"x": 432, "y": 711, "ayah": 67, "line": 6, "page": 119, "sura": 5, "width": 172, "height": 90}
{"x": 443, "y": 689, "ayah": null, "line": 6, "page": 119, "sura": null, "width": -12, "height": 22}
{"x": 325, "y": 714, "ayah": 67, "line": 6, "page": 119, "sura": 5, "width": 103, "height": 75}
{"x": 83, "y": 714, "ayah": 67, "line": 6, "page": 119, "sura": 5, "width": 232, "height": 80}
{"x": 1158, "y": 855, "ayah": 67, "line": 7, "page": 119, "sura": 5, "width": 57, "height": 74}
{"x": 1025, "y": 845, "ayah": 67, "line": 7, "page": 119, "sura": 5, "width": 125, "height": 88}
{"x": 1020, "y": 847, "ayah": null, "line": 7, "page": 119, "sura": null, "width": -3, "height": 23}
{"x": 965, "y": 847, "ayah": 67, "line": 7, "page": 119, "sura": 5, "width": 49, "height": 90}
{"x": 888, "y": 850, "ayah": 67, "line": 7, "page": 119, "sura": 5, "width": 65, "height": 63}
{"x": 838, "y": 843, "ayah": 67, "line": 7, "page": 119, "sura": 5, "width": 43, "height": 72}
{"x": 713, "y": 855, "ayah": 67, "line": 7, "page": 119, "sura": 5, "width": 120, "height": 75}
{"x": 599, "y": 845, "ayah": 67, "line": 7, "page": 119, "sura": 5, "width": 106, "height": 96}
{"x": 405, "y": 846, "ayah": 67, "line": 7, "page": 119, "sura": 5, "width": 186, "height": 96}
{"x": 289, "y": 840, "ayah": null, "line": 7, "page": 119, "sura": null, "width": 101, "height": 94}
{"x": 217, "y": 836, "ayah": 68, "line": 7, "page": 119, "sura": 5, "width": 72, "height": 91}
{"x": 88, "y": 845, "ayah": 68, "line": 7, "page": 119, "sura": 5, "width": 124, "height": 86}
{"x": 1054, "y": 981, "ayah": 68, "line": 8, "page": 119, "sura": 5, "width": 164, "height": 92}
{"x": 936, "y": 981, "ayah": 68, "line": 8, "page": 119, "sura": 5, "width": 102, "height": 103}
{"x": 862, "y": 990, "ayah": 68, "line": 8, "page": 119, "sura": 5, "width": 65, "height": 77}
{"x": 754, "y": 987, "ayah": 68, "line": 8, "page": 119, "sura": 5, "width": 96, "height": 82}
{"x": 657, "y": 981, "ayah": 68, "line": 8, "page": 119, "sura": 5, "width": 88, "height": 83}
{"x": 513, "y": 971, "ayah": 68, "line": 8, "page": 119, "sura": 5, "width": 133, "height": 97}
{"x": 337, "y": 980, "ayah": 68, "line": 8, "page": 119, "sura": 5, "width": 159, "height": 82}
{"x": 86, "y": 979, "ayah": 68, "line": 8, "page": 119, "sura": 5, "width": 235, "height": 93}
{"x": 1141, "y": 1120, "ayah": 68, "line": 9, "page": 119, "sura": 5, "width": 75, "height": 75}
{"x": 1050, "y": 1102, "ayah": 68, "line": 9, "page": 119, "sura": 5, "width": 82, "height": 108}
{"x": 909, "y": 1111, "ayah": 68, "line": 9, "page": 119, "sura": 5, "width": 124, "height": 103}
{"x": 842, "y": 1132, "ayah": 68, "line": 9, "page": 119, "sura": 5, "width": 56, "height": 68}
{"x": 711, "y": 1110, "ayah": 68, "line": 9, "page": 119, "sura": 5, "width": 120, "height": 101}
{"x": 704, "y": 1113, "ayah": null, "line": 9, "page": 119, "sura": null, "width": -3, "height": 24}
{"x": 446, "y": 1117, "ayah": 68, "line": 9, "page": 119, "sura": 5, "width": 252, "height": 94}
{"x": 350, "y": 1109, "ayah": 68, "line": 9, "page": 119, "sura": 5, "width": 88, "height": 92}
{"x": 237, "y": 1124, "ayah": 68, "line": 9, "page": 119, "sura": 5, "width": 101, "height": 84}
{"x": 183, "y": 1118, "ayah": 68, "line": 9, "page": 119, "sura": 5, "width": 45, "height": 61}
{"x": 87, "y": 1102, "ayah": 68, "line": 9, "page": 119, "sura": 5, "width": 88, "height": 106}
{"x": 1114, "y": 1254, "ayah": 68, "line": 10, "page": 119, "sura": 5, "width": 104, "height": 84}
{"x": 1039, "y": 1289, "ayah": 68, "line": 10, "page": 119, "sura": 5, "width": 60, "height": 41}
{"x": 934, "y": 1254, "ayah": 68, "line": 10, "page": 119, "sura": 5, "width": 95, "height": 87}
{"x": 771, "y": 1251, "ayah": 68, "line": 10, "page": 119, "sura": 5, "width": 151, "height": 78}
{"x": 642, "y": 1240, "ayah": 68, "line": 10, "page": 119, "sura": 5, "width": 118, "height": 89}
{"x": 632, "y": 1228, "ayah": null, "line": 10, "page": 119, "sura": null, "width": 3, "height": 23}
{"x": 569, "y": 1250, "ayah": 68, "line": 10, "page": 119, "sura": 5, "width": 63, "height": 70}
{"x": 470, "y": 1235, "ayah": 68, "line": 10, "page": 119, "sura": 5, "width": 92, "height": 91}
{"x": 398, "y": 1258, "ayah": 68, "line": 10, "page": 119, "sura": 5, "width": 66, "height": 76}
{"x": 263, "y": 1251, "ayah": 68, "line": 10, "page": 119, "sura": 5, "width": 124, "height": 82}
{"x": 85, "y": 1246, "ayah": 68, "line": 10, "page": 119, "sura": 5, "width": 172, "height": 95}
{"x": 1117, "y": 1376, "ayah": null, "line": 11, "page": 119, "sura": null, "width": 101, "height": 94}
{"x": 1059, "y": 1382, "ayah": 69, "line": 11, "page": 119, "sura": 5, "width": 58, "height": 85}
{"x": 947, "y": 1373, "ayah": 69, "line": 11, "page": 119, "sura": 5, "width": 102, "height": 95}
{"x": 806, "y": 1384, "ayah": 69, "line": 11, "page": 119, "sura": 5, "width": 129, "height": 80}
{"x": 595, "y": 1369, "ayah": 69, "line": 11, "page": 119, "sura": 5, "width": 203, "height": 97}
{"x": 478, "y": 1385, "ayah": 69, "line": 11, "page": 119, "sura": 5, "width": 108, "height": 73}
{"x": 265, "y": 1385, "ayah": 69, "line": 11, "page": 119, "sura": 5, "width": 205, "height": 88}
{"x": 83, "y": 1384, "ayah": 69, "line": 11, "page": 119, "sura": 5, "width": 169, "height": 80}
{"x": 1160, "y": 1533, "ayah": 69, "line": 12, "page": 119, "sura": 5, "width": 60, "height": 62}
{"x": 967, "y": 1532, "ayah": 69, "line": 12, "page": 119, "sura": 5, "width": 177, "height": 69}
{"x": 878, "y": 1520, "ayah": 69, "line": 12, "page": 119, "sura": 5, "width": 81, "height": 84}
{"x": 712, "y": 1518, "ayah": 69, "line": 12, "page": 119, "sura": 5, "width": 153, "height": 82}
{"x": 575, "y": 1517, "ayah": 69, "line": 12, "page": 119, "sura": 5, "width": 129, "height": 95}
{"x": 432, "y": 1523, "ayah": 69, "line": 12, "page": 119, "sura": 5, "width": 141, "height": 80}
{"x": 288, "y": 1520, "ayah": 69, "line": 12, "page": 119, "sura": 5, "width": 137, "height": 80}
{"x": 212, "y": 1515, "ayah": 69, "line": 12, "page": 119, "sura": 5, "width": 61, "height": 71}
{"x": 85, "y": 1507, "ayah": 69, "line": 12, "page": 119, "sura": 5, "width": 125, "height": 90}
{"x": 1065, "y": 1654, "ayah": 69, "line": 13, "page": 119, "sura": 5, "width": 152, "height": 90}
{"x": 988, "y": 1649, "ayah": 69, "line": 13, "page": 119, "sura": 5, "width": 67, "height": 76}
{"x": 906, "y": 1653, "ayah": 69, "line": 13, "page": 119, "sura": 5, "width": 74, "height": 94}
{"x": 754, "y": 1647, "ayah": 69, "line": 13, "page": 119, "sura": 5, "width": 140, "height": 85}
{"x": 633, "y": 1644, "ayah": null, "line": 13, "page": 119, "sura": null, "width": 102, "height": 94}
{"x": 508, "y": 1648, "ayah": 70, "line": 13, "page": 119, "sura": 5, "width": 125, "height": 69}
{"x": 348, "y": 1646, "ayah": 70, "line": 13, "page": 119, "sura": 5, "width": 147, "height": 72}
{"x": 161, "y": 1655, "ayah": 70, "line": 13, "page": 119, "sura": 5, "width": 171, "height": 81}
{"x": 85, "y": 1666, "ayah": 70, "line": 13, "page": 119, "sura": 5, "width": 67, "height": 80}
{"x": 1051, "y": 1793, "ayah": 70, "line": 14, "page": 119, "sura": 5, "width": 166, "height": 84}
{"x": 859, "y": 1778, "ayah": 70, "line": 14, "page": 119, "sura": 5, "width": 183, "height": 84}
{"x": 753, "y": 1787, "ayah": 70, "line": 14, "page": 119, "sura": 5, "width": 98, "height": 96}
{"x": 622, "y": 1783, "ayah": 70, "line": 14, "page": 119, "sura": 5, "width": 117, "height": 78}
{"x": 612, "y": 1772, "ayah": null, "line": 14, "page": 119, "sura": null, "width": 3, "height": 24}
{"x": 472, "y": 1777, "ayah": 70, "line": 14, "page": 119, "sura": 5, "width": 140, "height": 75}
{"x": 303, "y": 1785, "ayah": 70, "line": 14, "page": 119, "sura": 5, "width": 157, "height": 98}
{"x": 167, "y": 1783, "ayah": 70, "line": 14, "page": 119, "sura": 5, "width": 127, "height": 82}
{"x": 87, "y": 1792, "ayah": 70, "line": 14, "page": 119, "sura": 5, "width": 70, "height": 80}
{"x": 1175, "y": 1919, "ayah": 70, "line": 15, "page": 119, "sura": 5, "width": 43, "height": 66}
{"x": 1033, "y": 1921, "ayah": 70, "line": 15, "page": 119, "sura": 5, "width": 138, "height": 79}
{"x": 865, "y": 1911, "ayah": 70, "line": 15, "page": 119, "sura": 5, "width": 156, "height": 108}
{"x": 745, "y": 1912, "ayah": 70, "line": 15, "page": 119, "sura": 5, "width": 104, "height": 101}
{"x": 536, "y": 1905, "ayah": 70, "line": 15, "page": 119, "sura": 5, "width": 197, "height": 94}
{"x": 392, "y": 1911, "ayah": 70, "line": 15, "page": 119, "sura": 5, "width": 131, "height": 104}
{"x": 209, "y": 1917, "ayah": 70, "line": 15, "page": 119, "sura": 5, "width": 168, "height": 83}
{"x": 84, "y": 1912, "ayah": null, "line": 15, "page": 119, "sura": null, "width": 101, "height": 94}
