{"x": 1142, "y": 30, "ayah": 150, "line": 1, "page": 169, "sura": 7, "width": 85, "height": 80}
{"x": 1044, "y": 37, "ayah": 150, "line": 1, "page": 169, "sura": 7, "width": 87, "height": 94}
{"x": 911, "y": 36, "ayah": 150, "line": 1, "page": 169, "sura": 7, "width": 119, "height": 76}
{"x": 837, "y": 31, "ayah": 150, "line": 1, "page": 169, "sura": 7, "width": 59, "height": 87}
{"x": 699, "y": 33, "ayah": 150, "line": 1, "page": 169, "sura": 7, "width": 125, "height": 79}
{"x": 560, "y": 34, "ayah": 150, "line": 1, "page": 169, "sura": 7, "width": 133, "height": 74}
{"x": 465, "y": 31, "ayah": 150, "line": 1, "page": 169, "sura": 7, "width": 86, "height": 79}
{"x": 386, "y": 31, "ayah": 150, "line": 1, "page": 169, "sura": 7, "width": 67, "height": 68}
{"x": 258, "y": 39, "ayah": 150, "line": 1, "page": 169, "sura": 7, "width": 113, "height": 78}
{"x": 71, "y": 33, "ayah": 150, "line": 1, "page": 169, "sura": 7, "width": 176, "height": 81}
{"x": 1167, "y": 167, "ayah": 150, "line": 2, "page": 169, "sura": 7, "width": 59, "height": 78}
{"x": 1029, "y": 171, "ayah": 150, "line": 2, "page": 169, "sura": 7, "width": 128, "height": 74}
{"x": 1029, "y": 156, "ayah": null, "line": 2, "page": 169, "sura": null, "width": -7, "height": 22}
{"x": 847, "y": 160, "ayah": 150, "line": 2, "page": 169, "sura": 7, "width": 172, "height": 91}
{"x": 762, "y": 164, "ayah": 150, "line": 2, "page": 169, "sura": 7, "width": 69, "height": 84}
{"x": 624, "y": 162, "ayah": 150, "line": 2, "page": 169, "sura": 7, "width": 127, "height": 103}
{"x": 610, "y": 141, "ayah": null, "line": 2, "page": 169, "sura": null, "width": 6, "height": 24}
{"x": 488, "y": 160, "ayah": 150, "line": 2, "page": 169, "sura": 7, "width": 125, "height": 88}
{"x": 310, "y": 157, "ayah": 150, "line": 2, "page": 169, "sura": 7, "width": 163, "height": 113}
{"x": 188, "y": 155, "ayah": 150, "line": 2, "page": 169, "sura": 7, "width": 104, "height": 87}
{"x": 74, "y": 157, "ayah": 150, "line": 2, "page": 169, "sura": 7, "width": 100, "height": 103}
{"x": 1124, "y": 291, "ayah": 150, "line": 3, "page": 169, "sura": 7, "width": 105, "height": 89}
{"x": 1001, "y": 288, "ayah": 150, "line": 3, "page": 169, "sura": 7, "width": 107, "height": 95}
{"x": 908, "y": 296, "ayah": 150, "line": 3, "page": 169, "sura": 7, "width": 84, "height": 93}
{"x": 911, "y": 287, "ayah": null, "line": 3, "page": 169, "sura": null, "width": -10, "height": 21}
{"x": 825, "y": 292, "ayah": 150, "line": 3, "page": 169, "sura": 7, "width": 73, "height": 75}
{"x": 751, "y": 302, "ayah": 150, "line": 3, "page": 169, "sura": 7, "width": 60, "height": 76}
{"x": 689, "y": 283, "ayah": 150, "line": 3, "page": 169, "sura": 7, "width": 48, "height": 112}
{"x": 630, "y": 299, "ayah": 150, "line": 3, "page": 169, "sura": 7, "width": 48, "height": 88}
{"x": 510, "y": 298, "ayah": 150, "line": 3, "page": 169, "sura": 7, "width": 108, "height": 100}
{"x": 218, "y": 298, "ayah": 150, "line": 3, "page": 169, "sura": 7, "width": 277, "height": 87}
{"x": 72, "y": 296, "ayah": 150, "line": 3, "page": 169, "sura": 7, "width": 127, "height": 78}
{"x": 1044, "y": 427, "ayah": 150, "line": 4, "page": 169, "sura": 7, "width": 184, "height": 96}
{"x": 964, "y": 434, "ayah": 150, "line": 4, "page": 169, "sura": 7, "width": 64, "height": 70}
{"x": 801, "y": 427, "ayah": 150, "line": 4, "page": 169, "sura": 7, "width": 155, "height": 87}
{"x": 682, "y": 453, "ayah": 150, "line": 4, "page": 169, "sura": 7, "width": 103, "height": 75}
{"x": 497, "y": 424, "ayah": 150, "line": 4, "page": 169, "sura": 7, "width": 173, "height": 75}
{"x": 417, "y": 436, "ayah": 150, "line": 4, "page": 169, "sura": 7, "width": 57, "height": 75}
{"x": 273, "y": 433, "ayah": 150, "line": 4, "page": 169, "sura": 7, "width": 136, "height": 91}
{"x": 210, "y": 444, "ayah": 150, "line": 4, "page": 169, "sura": 7, "width": 51, "height": 89}
{"x": 74, "y": 432, "ayah": 150, "line": 4, "page": 169, "sura": 7, "width": 121, "height": 85}
{"x": 1027, "y": 553, "ayah": 150, "line": 5, "page": 169, "sura": 7, "width": 199, "height": 94}
{"x": 904, "y": 560, "ayah": null, "line": 5, "page": 169, "sura": null, "width": 101, "height": 94}
{"x": 810, "y": 562, "ayah": 151, "line": 5, "page": 169, "sura": 7, "width": 94, "height": 76}
{"x": 714, "y": 574, "ayah": 151, "line": 5, "page": 169, "sura": 7, "width": 84, "height": 84}
{"x": 585, "y": 565, "ayah": 151, "line": 5, "page": 169, "sura": 7, "width": 116, "height": 90}
{"x": 534, "y": 580, "ayah": 151, "line": 5, "page": 169, "sura": 7, "width": 45, "height": 79}
{"x": 385, "y": 561, "ayah": 151, "line": 5, "page": 169, "sura": 7, "width": 138, "height": 98}
{"x": 178, "y": 558, "ayah": 151, "line": 5, "page": 169, "sura": 7, "width": 191, "height": 89}
{"x": 74, "y": 585, "ayah": 151, "line": 5, "page": 169, "sura": 7, "width": 92, "height": 71}
{"x": 1045, "y": 699, "ayah": 151, "line": 6, "page": 169, "sura": 7, "width": 184, "height": 83}
{"x": 1042, "y": 683, "ayah": null, "line": 6, "page": 169, "sura": null, "width": -5, "height": 23}
{"x": 922, "y": 692, "ayah": 151, "line": 6, "page": 169, "sura": 7, "width": 112, "height": 86}
{"x": 780, "y": 691, "ayah": 151, "line": 6, "page": 169, "sura": 7, "width": 128, "height": 110}
{"x": 538, "y": 700, "ayah": 151, "line": 6, "page": 169, "sura": 7, "width": 226, "height": 85}
{"x": 418, "y": 694, "ayah": null, "line": 6, "page": 169, "sura": null, "width": 101, "height": 94}
{"x": 345, "y": 696, "ayah": 152, "line": 6, "page": 169, "sura": 7, "width": 73, "height": 92}
{"x": 230, "y": 686, "ayah": 152, "line": 6, "page": 169, "sura": 7, "width": 100, "height": 96}
{"x": 74, "y": 686, "ayah": 152, "line": 6, "page": 169, "sura": 7, "width": 139, "height": 88}
{"x": 1082, "y": 832, "ayah": 152, "line": 7, "page": 169, "sura": 7, "width": 143, "height": 84}
{"x": 887, "y": 819, "ayah": 152, "line": 7, "page": 169, "sura": 7, "width": 186, "height": 115}
{"x": 718, "y": 836, "ayah": 152, "line": 7, "page": 169, "sura": 7, "width": 156, "height": 78}
{"x": 643, "y": 853, "ayah": 152, "line": 7, "page": 169, "sura": 7, "width": 64, "height": 67}
{"x": 499, "y": 838, "ayah": 152, "line": 7, "page": 169, "sura": 7, "width": 129, "height": 96}
{"x": 374, "y": 819, "ayah": 152, "line": 7, "page": 169, "sura": 7, "width": 110, "height": 104}
{"x": 330, "y": 855, "ayah": 152, "line": 7, "page": 169, "sura": 7, "width": 49, "height": 70}
{"x": 202, "y": 830, "ayah": 152, "line": 7, "page": 169, "sura": 7, "width": 119, "height": 89}
{"x": 83, "y": 823, "ayah": 152, "line": 7, "page": 169, "sura": 7, "width": 109, "height": 90}
{"x": 81, "y": 810, "ayah": null, "line": 7, "page": 169, "sura": null, "width": -6, "height": 21}
{"x": 1061, "y": 966, "ayah": 152, "line": 8, "page": 169, "sura": 7, "width": 161, "height": 84}
{"x": 942, "y": 964, "ayah": 152, "line": 8, "page": 169, "sura": 7, "width": 110, "height": 97}
{"x": 745, "y": 966, "ayah": 152, "line": 8, "page": 169, "sura": 7, "width": 186, "height": 92}
{"x": 622, "y": 962, "ayah": null, "line": 8, "page": 169, "sura": null, "width": 101, "height": 94}
{"x": 482, "y": 958, "ayah": 153, "line": 8, "page": 169, "sura": 7, "width": 140, "height": 95}
{"x": 358, "y": 964, "ayah": 153, "line": 8, "page": 169, "sura": 7, "width": 115, "height": 88}
{"x": 153, "y": 968, "ayah": 153, "line": 8, "page": 169, "sura": 7, "width": 194, "height": 92}
{"x": 78, "y": 960, "ayah": 153, "line": 8, "page": 169, "sura": 7, "width": 63, "height": 81}
{"x": 1139, "y": 1107, "ayah": 153, "line": 9, "page": 169, "sura": 7, "width": 87, "height": 76}
{"x": 1074, "y": 1105, "ayah": 153, "line": 9, "page": 169, "sura": 7, "width": 56, "height": 81}
{"x": 941, "y": 1107, "ayah": 153, "line": 9, "page": 169, "sura": 7, "width": 120, "height": 77}
{"x": 764, "y": 1107, "ayah": 153, "line": 9, "page": 169, "sura": 7, "width": 161, "height": 78}
{"x": 703, "y": 1103, "ayah": 153, "line": 9, "page": 169, "sura": 7, "width": 46, "height": 88}
{"x": 590, "y": 1103, "ayah": 153, "line": 9, "page": 169, "sura": 7, "width": 97, "height": 78}
{"x": 521, "y": 1111, "ayah": 153, "line": 9, "page": 169, "sura": 7, "width": 55, "height": 71}
{"x": 376, "y": 1110, "ayah": 153, "line": 9, "page": 169, "sura": 7, "width": 131, "height": 73}
{"x": 221, "y": 1098, "ayah": 153, "line": 9, "page": 169, "sura": 7, "width": 136, "height": 85}
{"x": 74, "y": 1103, "ayah": 153, "line": 9, "page": 169, "sura": 7, "width": 140, "height": 87}
{"x": 1122, "y": 1230, "ayah": null, "line": 10, "page": 169, "sura": null, "width": 101, "height": 94}
{"x": 1020, "y": 1237, "ayah": 154, "line": 10, "page": 169, "sura": 7, "width": 102, "height": 78}
{"x": 864, "y": 1235, "ayah": 154, "line": 10, "page": 169, "sura": 7, "width": 145, "height": 68}
{"x": 785, "y": 1246, "ayah": 154, "line": 10, "page": 169, "sura": 7, "width": 70, "height": 68}
{"x": 656, "y": 1235, "ayah": 154, "line": 10, "page": 169, "sura": 7, "width": 120, "height": 84}
{"x": 448, "y": 1237, "ayah": 154, "line": 10, "page": 169, "sura": 7, "width": 200, "height": 83}
{"x": 350, "y": 1230, "ayah": 154, "line": 10, "page": 169, "sura": 7, "width": 84, "height": 74}
{"x": 168, "y": 1225, "ayah": 154, "line": 10, "page": 169, "sura": 7, "width": 172, "height": 105}
{"x": 170, "y": 1210, "ayah": null, "line": 10, "page": 169, "sura": null, "width": -12, "height": 24}
{"x": 79, "y": 1244, "ayah": 154, "line": 10, "page": 169, "sura": 7, "width": 76, "height": 81}
{"x": 1077, "y": 1362, "ayah": 154, "line": 11, "page": 169, "sura": 7, "width": 154, "height": 92}
{"x": 948, "y": 1369, "ayah": 154, "line": 11, "page": 169, "sura": 7, "width": 116, "height": 71}
{"x": 807, "y": 1361, "ayah": 154, "line": 11, "page": 169, "sura": 7, "width": 132, "height": 86}
{"x": 688, "y": 1356, "ayah": 154, "line": 11, "page": 169, "sura": 7, "width": 106, "height": 96}
{"x": 609, "y": 1370, "ayah": 154, "line": 11, "page": 169, "sura": 7, "width": 68, "height": 95}
{"x": 488, "y": 1379, "ayah": 154, "line": 11, "page": 169, "sura": 7, "width": 110, "height": 90}
{"x": 339, "y": 1375, "ayah": 154, "line": 11, "page": 169, "sura": 7, "width": 141, "height": 79}
{"x": 226, "y": 1364, "ayah": null, "line": 11, "page": 169, "sura": null, "width": 101, "height": 94}
{"x": 71, "y": 1373, "ayah": 155, "line": 11, "page": 169, "sura": 7, "width": 155, "height": 76}
{"x": 1111, "y": 1515, "ayah": 155, "line": 12, "page": 169, "sura": 7, "width": 117, "height": 72}
{"x": 992, "y": 1504, "ayah": 155, "line": 12, "page": 169, "sura": 7, "width": 111, "height": 82}
{"x": 840, "y": 1508, "ayah": 155, "line": 12, "page": 169, "sura": 7, "width": 146, "height": 82}
{"x": 729, "y": 1501, "ayah": 155, "line": 12, "page": 169, "sura": 7, "width": 100, "height": 81}
{"x": 555, "y": 1507, "ayah": 155, "line": 12, "page": 169, "sura": 7, "width": 157, "height": 81}
{"x": 548, "y": 1485, "ayah": null, "line": 12, "page": 169, "sura": null, "width": 1, "height": 24}
{"x": 453, "y": 1504, "ayah": 155, "line": 12, "page": 169, "sura": 7, "width": 93, "height": 66}
{"x": 277, "y": 1498, "ayah": 155, "line": 12, "page": 169, "sura": 7, "width": 167, "height": 104}
{"x": 75, "y": 1496, "ayah": 155, "line": 12, "page": 169, "sura": 7, "width": 186, "height": 91}
{"x": 1156, "y": 1634, "ayah": 155, "line": 13, "page": 169, "sura": 7, "width": 68, "height": 74}
{"x": 1063, "y": 1644, "ayah": 155, "line": 13, "page": 169, "sura": 7, "width": 78, "height": 84}
{"x": 1006, "y": 1636, "ayah": 155, "line": 13, "page": 169, "sura": 7, "width": 43, "height": 85}
{"x": 878, "y": 1640, "ayah": 155, "line": 13, "page": 169, "sura": 7, "width": 122, "height": 81}
{"x": 649, "y": 1633, "ayah": 155, "line": 13, "page": 169, "sura": 7, "width": 214, "height": 87}
{"x": 585, "y": 1651, "ayah": 155, "line": 13, "page": 169, "sura": 7, "width": 56, "height": 76}
{"x": 496, "y": 1637, "ayah": 155, "line": 13, "page": 169, "sura": 7, "width": 80, "height": 82}
{"x": 365, "y": 1647, "ayah": 155, "line": 13, "page": 169, "sura": 7, "width": 118, "height": 84}
{"x": 367, "y": 1625, "ayah": null, "line": 13, "page": 169, "sura": null, "width": -7, "height": 24}
{"x": 219, "y": 1629, "ayah": 155, "line": 13, "page": 169, "sura": 7, "width": 138, "height": 95}
{"x": 171, "y": 1639, "ayah": 155, "line": 13, "page": 169, "sura": 7, "width": 36, "height": 89}
{"x": 75, "y": 1639, "ayah": 155, "line": 13, "page": 169, "sura": 7, "width": 88, "height": 79}
{"x": 1048, "y": 1773, "ayah": 155, "line": 14, "page": 169, "sura": 7, "width": 177, "height": 78}
{"x": 971, "y": 1771, "ayah": 155, "line": 14, "page": 169, "sura": 7, "width": 66, "height": 80}
{"x": 971, "y": 1746, "ayah": null, "line": 14, "page": 169, "sura": null, "width": 1, "height": 24}
{"x": 924, "y": 1776, "ayah": 155, "line": 14, "page": 169, "sura": 7, "width": 45, "height": 86}
{"x": 855, "y": 1784, "ayah": 155, "line": 14, "page": 169, "sura": 7, "width": 58, "height": 74}
{"x": 783, "y": 1761, "ayah": 155, "line": 14, "page": 169, "sura": 7, "width": 59, "height": 98}
{"x": 647, "y": 1766, "ayah": 155, "line": 14, "page": 169, "sura": 7, "width": 128, "height": 86}
{"x": 523, "y": 1756, "ayah": 155, "line": 14, "page": 169, "sura": 7, "width": 109, "height": 98}
{"x": 458, "y": 1787, "ayah": 155, "line": 14, "page": 169, "sura": 7, "width": 52, "height": 75}
{"x": 387, "y": 1783, "ayah": 155, "line": 14, "page": 169, "sura": 7, "width": 58, "height": 65}
{"x": 278, "y": 1772, "ayah": 155, "line": 14, "page": 169, "sura": 7, "width": 98, "height": 67}
{"x": 75, "y": 1777, "ayah": 155, "line": 14, "page": 169, "sura": 7, "width": 190, "height": 76}
{"x": 1170, "y": 1915, "ayah": 155, "line": 15, "page": 169, "sura": 7, "width": 56, "height": 71}
{"x": 1068, "y": 1907, "ayah": 155, "line": 15, "page": 169, "sura": 7, "width": 91, "height": 66}
{"x": 1070, "y": 1880, "ayah": null, "line": 15, "page": 169, "sura": null, "width": -9, "height": 24}
{"x": 990, "y": 1899, "ayah": 155, "line": 15, "page": 169, "sura": 7, "width": 68, "height": 75}
{"x": 897, "y": 1902, "ayah": 155, "line": 15, "page": 169, "sura": 7, "width": 86, "height": 98}
{"x": 763, "y": 1904, "ayah": 155, "line": 15, "page": 169, "sura": 7, "width": 123, "height": 84}
{"x": 707, "y": 1906, "ayah": 155, "line": 15, "page": 169, "sura": 7, "width": 56, "height": 66}
{"x": 555, "y": 1906, "ayah": 155, "line": 15, "page": 169, "sura": 7, "width": 145, "height": 78}
{"x": 545, "y": 1880, "ayah": null, "line": 15, "page": 169, "sura": null, "width": 3, "height": 24}
{"x": 443, "y": 1898, "ayah": 155, "line": 15, "page": 169, "sura": 7, "width": 102, "height": 88}
{"x": 355, "y": 1905, "ayah": 155, "line": 15, "page": 169, "sura": 7, "width": 76, "height": 83}
{"x": 181, "y": 1907, "ayah": 155, "line": 15, "page": 169, "sura": 7, "width": 174, "height": 95}
{"x": 70, "y": 1900, "ayah": null, "line": 15, "page": 169, "sura": null, "width": 101, "height": 94}
{"x": 1142, "y": 30, "ayah": 150, "line": 1, "page": 169, "sura": 7, "width": 85, "height": 80}
{"x": 1044, "y": 37, "ayah": 150, "line": 1, "page": 169, "sura": 7, "width": 87, "height": 94}
{"x": 911, "y": 36, "ayah": 150, "line": 1, "page": 169, "sura": 7, "width": 119, "height": 76}
{"x": 837, "y": 31, "ayah": 150, "line": 1, "page": 169, "sura": 7, "width": 59, "height": 87}
{"x": 699, "y": 33, "ayah": 150, "line": 1, "page": 169, "sura": 7, "width": 125, "height": 79}
{"x": 560, "y": 34, "ayah": 150, "line": 1, "page": 169, "sura": 7, "width": 133, "height": 74}
{"x": 465, "y": 31, "ayah": 150, "line": 1, "page": 169, "sura": 7, "width": 86, "height": 79}
{"x": 386, "y": 31, "ayah": 150, "line": 1, "page": 169, "sura": 7, "width": 67, "height": 68}
{"x": 258, "y": 39, "ayah": 150, "line": 1, "page": 169, "sura": 7, "width": 113, "height": 78}
{"x": 71, "y": 33, "ayah": 150, "line": 1, "page": 169, "sura": 7, "width": 176, "height": 81}
{"x": 1167, "y": 167, "ayah": 150, "line": 2, "page": 169, "sura": 7, "width": 59, "height": 78}
{"x": 1029, "y": 171, "ayah": 150, "line": 2, "page": 169, "sura": 7, "width": 128, "height": 74}
{"x": 1029, "y": 156, "ayah": null, "line": 2, "page": 169, "sura": null, "width": -7, "height": 22}
{"x": 847, "y": 160, "ayah": 150, "line": 2, "page": 169, "sura": 7, "width": 172, "height": 91}
{"x": 762, "y": 164, "ayah": 150, "line": 2, "page": 169, "sura": 7, "width": 69, "height": 84}
{"x": 624, "y": 162, "ayah": 150, "line": 2, "page": 169, "sura": 7, "width": 127, "height": 103}
{"x": 610, "y": 141, "ayah": null, "line": 2, "page": 169, "sura": null, "width": 6, "height": 24}
{"x": 488, "y": 160, "ayah": 150, "line": 2, "page": 169, "sura": 7, "width": 125, "height": 88}
{"x": 310, "y": 157, "ayah": 150, "line": 2, "page": 169, "sura": 7, "width": 163, "height": 113}
{"x": 188, "y": 155, "ayah": 150, "line": 2, "page": 169, "sura": 7, "width": 104, "height": 87}
{"x": 74, "y": 157, "ayah": 150, "line": 2, "page": 169, "sura": 7, "width": 100, "height": 103}
{"x": 1124, "y": 291, "ayah": 150, "line": 3, "page": 169, "sura": 7, "width": 105, "height": 89}
{"x": 1001, "y": 288, "ayah": 150, "line": 3, "page": 169, "sura": 7, "width": 107, "height": 95}
{"x": 908, "y": 296, "ayah": 150, "line": 3, "page": 169, "sura": 7, "width": 84, "height": 93}
{"x": 911, "y": 287, "ayah": null, "line": 3, "page": 169, "sura": null, "width": -10, "height": 21}
{"x": 825, "y": 292, "ayah": 150, "line": 3, "page": 169, "sura": 7, "width": 73, "height": 75}
{"x": 751, "y": 302, "ayah": 150, "line": 3, "page": 169, "sura": 7, "width": 60, "height": 76}
{"x": 689, "y": 283, "ayah": 150, "line": 3, "page": 169, "sura": 7, "width": 48, "height": 112}
{"x": 630, "y": 299, "ayah": 150, "line": 3, "page": 169, "sura": 7, "width": 48, "height": 88}
{"x": 510, "y": 298, "ayah": 150, "line": 3, "page": 169, "sura": 7, "width": 108, "height": 100}
{"x": 218, "y": 298, "ayah": 150, "line": 3, "page": 169, "sura": 7, "width": 277, "height": 87}
{"x": 72, "y": 296, "ayah": 150, "line": 3, "page": 169, "sura": 7, "width": 127, "height": 78}
{"x": 1044, "y": 427, "ayah": 150, "line": 4, "page": 169, "sura": 7, "width": 184, "height": 96}
{"x": 964, "y": 434, "ayah": 150, "line": 4, "page": 169, "sura": 7, "width": 64, "height": 70}
{"x": 801, "y": 427, "ayah": 150, "line": 4, "page": 169, "sura": 7, "width": 155, "height": 87}
{"x": 682, "y": 453, "ayah": 150, "line": 4, "page": 169, "sura": 7, "width": 103, "height": 75}
{"x": 497, "y": 424, "ayah": 150, "line": 4, "page": 169, "sura": 7, "width": 173, "height": 75}
{"x": 417, "y": 436, "ayah": 150, "line": 4, "page": 169, "sura": 7, "width": 57, "height": 75}
{"x": 273, "y": 433, "ayah": 150, "line": 4, "page": 169, "sura": 7, "width": 136, "height": 91}
{"x": 210, "y": 444, "ayah": 150, "line": 4, "page": 169, "sura": 7, "width": 51, "height": 89}
{"x": 74, "y": 432, "ayah": 150, "line": 4, "page": 169, "sura": 7, "width": 121, "height": 85}
{"x": 1027, "y": 553, "ayah": 150, "line": 5, "page": 169, "sura": 7, "width": 199, "height": 94}
{"x": 904, "y": 560, "ayah": null, "line": 5, "page": 169, "sura": null, "width": 101, "height": 94}
{"x": 810, "y": 562, "ayah": 151, "line": 5, "page": 169, "sura": 7, "width": 94, "height": 76}
{"x": 714, "y": 574, "ayah": 151, "line": 5, "page": 169, "sura": 7, "width": 84, "height": 84}
{"x": 585, "y": 565, "ayah": 151, "line": 5, "page": 169, "sura": 7, "width": 116, "height": 90}
{"x": 534, "y": 580, "ayah": 151, "line": 5, "page": 169, "sura": 7, "width": 45, "height": 79}
{"x": 385, "y": 561, "ayah": 151, "line": 5, "page": 169, "sura": 7, "width": 138, "height": 98}
{"x": 178, "y": 558, "ayah": 151, "line": 5, "page": 169, "sura": 7, "width": 191, "height": 89}
{"x": 74, "y": 585, "ayah": 151, "line": 5, "page": 169, "sura": 7, "width": 92, "height": 71}
{"x": 1045, "y": 699, "ayah": 151, "line": 6, "page": 169, "sura": 7, "width": 184, "height": 83}
{"x": 1042, "y": 683, "ayah": null, "line": 6, "page": 169, "sura": null, "width": -5, "height": 23}
{"x": 922, "y": 692, "ayah": 151, "line": 6, "page": 169, "sura": 7, "width": 112, "height": 86}
{"x": 780, "y": 691, "ayah": 151, "line": 6, "page": 169, "sura": 7, "width": 128, "height": 110}
{"x": 538, "y": 700, "ayah": 151, "line": 6, "page": 169, "sura": 7, "width": 226, "height": 85}
{"x": 418, "y": 694, "ayah": null, "line": 6, "page": 169, "sura": null, "width": 101, "height": 94}
{"x": 345, "y": 696, "ayah": 152, "line": 6, "page": 169, "sura": 7, "width": 73, "height": 92}
{"x": 230, "y": 686, "ayah": 152, "line": 6, "page": 169, "sura": 7, "width": 100, "height": 96}
{"x": 74, "y": 686, "ayah": 152, "line": 6, "page": 169, "sura": 7, "width": 139, "height": 88}
{"x": 1082, "y": 832, "ayah": 152, "line": 7, "page": 169, "sura": 7, "width": 143, "height": 84}
{"x": 887, "y": 819, "ayah": 152, "line": 7, "page": 169, "sura": 7, "width": 186, "height": 115}
{"x": 718, "y": 836, "ayah": 152, "line": 7, "page": 169, "sura": 7, "width": 156, "height": 78}
{"x": 643, "y": 853, "ayah": 152, "line": 7, "page": 169, "sura": 7, "width": 64, "height": 67}
{"x": 499, "y": 838, "ayah": 152, "line": 7, "page": 169, "sura": 7, "width": 129, "height": 96}
{"x": 374, "y": 819, "ayah": 152, "line": 7, "page": 169, "sura": 7, "width": 110, "height": 104}
{"x": 330, "y": 855, "ayah": 152, "line": 7, "page": 169, "sura": 7, "width": 49, "height": 70}
{"x": 202, "y": 830, "ayah": 152, "line": 7, "page": 169, "sura": 7, "width": 119, "height": 89}
{"x": 83, "y": 823, "ayah": 152, "line": 7, "page": 169, "sura": 7, "width": 109, "height": 90}
{"x": 81, "y": 810, "ayah": null, "line": 7, "page": 169, "sura": null, "width": -6, "height": 21}
{"x": 1061, "y": 966, "ayah": 152, "line": 8, "page": 169, "sura": 7, "width": 161, "height": 84}
{"x": 942, "y": 964, "ayah": 152, "line": 8, "page": 169, "sura": 7, "width": 110, "height": 97}
{"x": 745, "y": 966, "ayah": 152, "line": 8, "page": 169, "sura": 7, "width": 186, "height": 92}
{"x": 622, "y": 962, "ayah": null, "line": 8, "page": 169, "sura": null, "width": 101, "height": 94}
{"x": 482, "y": 958, "ayah": 153, "line": 8, "page": 169, "sura": 7, "width": 140, "height": 95}
{"x": 358, "y": 964, "ayah": 153, "line": 8, "page": 169, "sura": 7, "width": 115, "height": 88}
{"x": 153, "y": 968, "ayah": 153, "line": 8, "page": 169, "sura": 7, "width": 194, "height": 92}
{"x": 78, "y": 960, "ayah": 153, "line": 8, "page": 169, "sura": 7, "width": 63, "height": 81}
{"x": 1139, "y": 1107, "ayah": 153, "line": 9, "page": 169, "sura": 7, "width": 87, "height": 76}
{"x": 1074, "y": 1105, "ayah": 153, "line": 9, "page": 169, "sura": 7, "width": 56, "height": 81}
{"x": 941, "y": 1107, "ayah": 153, "line": 9, "page": 169, "sura": 7, "width": 120, "height": 77}
{"x": 764, "y": 1107, "ayah": 153, "line": 9, "page": 169, "sura": 7, "width": 161, "height": 78}
{"x": 703, "y": 1103, "ayah": 153, "line": 9, "page": 169, "sura": 7, "width": 46, "height": 88}
{"x": 590, "y": 1103, "ayah": 153, "line": 9, "page": 169, "sura": 7, "width": 97, "height": 78}
{"x": 521, "y": 1111, "ayah": 153, "line": 9, "page": 169, "sura": 7, "width": 55, "height": 71}
{"x": 376, "y": 1110, "ayah": 153, "line": 9, "page": 169, "sura": 7, "width": 131, "height": 73}
{"x": 221, "y": 1098, "ayah": 153, "line": 9, "page": 169, "sura": 7, "width": 136, "height": 85}
{"x": 74, "y": 1103, "ayah": 153, "line": 9, "page": 169, "sura": 7, "width": 140, "height": 87}
{"x": 1122, "y": 1230, "ayah": null, "line": 10, "page": 169, "sura": null, "width": 101, "height": 94}
{"x": 1020, "y": 1237, "ayah": 154, "line": 10, "page": 169, "sura": 7, "width": 102, "height": 78}
{"x": 864, "y": 1235, "ayah": 154, "line": 10, "page": 169, "sura": 7, "width": 145, "height": 68}
{"x": 785, "y": 1246, "ayah": 154, "line": 10, "page": 169, "sura": 7, "width": 70, "height": 68}
{"x": 656, "y": 1235, "ayah": 154, "line": 10, "page": 169, "sura": 7, "width": 120, "height": 84}
{"x": 448, "y": 1237, "ayah": 154, "line": 10, "page": 169, "sura": 7, "width": 200, "height": 83}
{"x": 350, "y": 1230, "ayah": 154, "line": 10, "page": 169, "sura": 7, "width": 84, "height": 74}
{"x": 168, "y": 1225, "ayah": 154, "line": 10, "page": 169, "sura": 7, "width": 172, "height": 105}
{"x": 170, "y": 1210, "ayah": null, "line": 10, "page": 169, "sura": null, "width": -12, "height": 24}
{"x": 79, "y": 1244, "ayah": 154, "line": 10, "page": 169, "sura": 7, "width": 76, "height": 81}
{"x": 1077, "y": 1362, "ayah": 154, "line": 11, "page": 169, "sura": 7, "width": 154, "height": 92}
{"x": 948, "y": 1369, "ayah": 154, "line": 11, "page": 169, "sura": 7, "width": 116, "height": 71}
{"x": 807, "y": 1361, "ayah": 154, "line": 11, "page": 169, "sura": 7, "width": 132, "height": 86}
{"x": 688, "y": 1356, "ayah": 154, "line": 11, "page": 169, "sura": 7, "width": 106, "height": 96}
{"x": 609, "y": 1370, "ayah": 154, "line": 11, "page": 169, "sura": 7, "width": 68, "height": 95}
{"x": 488, "y": 1379, "ayah": 154, "line": 11, "page": 169, "sura": 7, "width": 110, "height": 90}
{"x": 339, "y": 1375, "ayah": 154, "line": 11, "page": 169, "sura": 7, "width": 141, "height": 79}
{"x": 226, "y": 1364, "ayah": null, "line": 11, "page": 169, "sura": null, "width": 101, "height": 94}
{"x": 71, "y": 1373, "ayah": 155, "line": 11, "page": 169, "sura": 7, "width": 155, "height": 76}
{"x": 1111, "y": 1515, "ayah": 155, "line": 12, "page": 169, "sura": 7, "width": 117, "height": 72}
{"x": 992, "y": 1504, "ayah": 155, "line": 12, "page": 169, "sura": 7, "width": 111, "height": 82}
{"x": 840, "y": 1508, "ayah": 155, "line": 12, "page": 169, "sura": 7, "width": 146, "height": 82}
{"x": 729, "y": 1501, "ayah": 155, "line": 12, "page": 169, "sura": 7, "width": 100, "height": 81}
{"x": 555, "y": 1507, "ayah": 155, "line": 12, "page": 169, "sura": 7, "width": 157, "height": 81}
{"x": 548, "y": 1485, "ayah": null, "line": 12, "page": 169, "sura": null, "width": 1, "height": 24}
{"x": 453, "y": 1504, "ayah": 155, "line": 12, "page": 169, "sura": 7, "width": 93, "height": 66}
{"x": 277, "y": 1498, "ayah": 155, "line": 12, "page": 169, "sura": 7, "width": 167, "height": 104}
{"x": 75, "y": 1496, "ayah": 155, "line": 12, "page": 169, "sura": 7, "width": 186, "height": 91}
{"x": 1156, "y": 1634, "ayah": 155, "line": 13, "page": 169, "sura": 7, "width": 68, "height": 74}
{"x": 1063, "y": 1644, "ayah": 155, "line": 13, "page": 169, "sura": 7, "width": 78, "height": 84}
{"x": 1006, "y": 1636, "ayah": 155, "line": 13, "page": 169, "sura": 7, "width": 43, "height": 85}
{"x": 878, "y": 1640, "ayah": 155, "line": 13, "page": 169, "sura": 7, "width": 122, "height": 81}
{"x": 649, "y": 1633, "ayah": 155, "line": 13, "page": 169, "sura": 7, "width": 214, "height": 87}
{"x": 585, "y": 1651, "ayah": 155, "line": 13, "page": 169, "sura": 7, "width": 56, "height": 76}
{"x": 496, "y": 1637, "ayah": 155, "line": 13, "page": 169, "sura": 7, "width": 80, "height": 82}
{"x": 365, "y": 1647, "ayah": 155, "line": 13, "page": 169, "sura": 7, "width": 118, "height": 84}
{"x": 367, "y": 1625, "ayah": null, "line": 13, "page": 169, "sura": null, "width": -7, "height": 24}
{"x": 219, "y": 1629, "ayah": 155, "line": 13, "page": 169, "sura": 7, "width": 138, "height": 95}
{"x": 171, "y": 1639, "ayah": 155, "line": 13, "page": 169, "sura": 7, "width": 36, "height": 89}
{"x": 75, "y": 1639, "ayah": 155, "line": 13, "page": 169, "sura": 7, "width": 88, "height": 79}
{"x": 1048, "y": 1773, "ayah": 155, "line": 14, "page": 169, "sura": 7, "width": 177, "height": 78}
{"x": 971, "y": 1771, "ayah": 155, "line": 14, "page": 169, "sura": 7, "width": 66, "height": 80}
{"x": 971, "y": 1746, "ayah": null, "line": 14, "page": 169, "sura": null, "width": 1, "height": 24}
{"x": 924, "y": 1776, "ayah": 155, "line": 14, "page": 169, "sura": 7, "width": 45, "height": 86}
{"x": 855, "y": 1784, "ayah": 155, "line": 14, "page": 169, "sura": 7, "width": 58, "height": 74}
{"x": 783, "y": 1761, "ayah": 155, "line": 14, "page": 169, "sura": 7, "width": 59, "height": 98}
{"x": 647, "y": 1766, "ayah": 155, "line": 14, "page": 169, "sura": 7, "width": 128, "height": 86}
{"x": 523, "y": 1756, "ayah": 155, "line": 14, "page": 169, "sura": 7, "width": 109, "height": 98}
{"x": 458, "y": 1787, "ayah": 155, "line": 14, "page": 169, "sura": 7, "width": 52, "height": 75}
{"x": 387, "y": 1783, "ayah": 155, "line": 14, "page": 169, "sura": 7, "width": 58, "height": 65}
{"x": 278, "y": 1772, "ayah": 155, "line": 14, "page": 169, "sura": 7, "width": 98, "height": 67}
{"x": 75, "y": 1777, "ayah": 155, "line": 14, "page": 169, "sura": 7, "width": 190, "height": 76}
{"x": 1170, "y": 1915, "ayah": 155, "line": 15, "page": 169, "sura": 7, "width": 56, "height": 71}
{"x": 1068, "y": 1907, "ayah": 155, "line": 15, "page": 169, "sura": 7, "width": 91, "height": 66}
{"x": 1070, "y": 1880, "ayah": null, "line": 15, "page": 169, "sura": null, "width": -9, "height": 24}
{"x": 990, "y": 1899, "ayah": 155, "line": 15, "page": 169, "sura": 7, "width": 68, "height": 75}
{"x": 897, "y": 1902, "ayah": 155, "line": 15, "page": 169, "sura": 7, "width": 86, "height": 98}
{"x": 763, "y": 1904, "ayah": 155, "line": 15, "page": 169, "sura": 7, "width": 123, "height": 84}
{"x": 707, "y": 1906, "ayah": 155, "line": 15, "page": 169, "sura": 7, "width": 56, "height": 66}
{"x": 555, "y": 1906, "ayah": 155, "line": 15, "page": 169, "sura": 7, "width": 145, "height": 78}
{"x": 545, "y": 1880, "ayah": null, "line": 15, "page": 169, "sura": null, "width": 3, "height": 24}
{"x": 443, "y": 1898, "ayah": 155, "line": 15, "page": 169, "sura": 7, "width": 102, "height": 88}
{"x": 355, "y": 1905, "ayah": 155, "line": 15, "page": 169, "sura": 7, "width": 76, "height": 83}
{"x": 181, "y": 1907, "ayah": 155, "line": 15, "page": 169, "sura": 7, "width": 174, "height": 95}
{"x": 70, "y": 1900, "ayah": null, "line": 15, "page": 169, "sura": null, "width": 101, "height": 94}
